{"isHard":false,"numberBullets":31,"bulletsColor":[],"bulletItems":{"BombBulletItem":0,"ElectricBulletBallItem":0,"RainbowBulletBallItem":0,"RocketBulletItem":0},"starsTarget":[25000,30000,40000],"missionType":"CollectBubbles","colors":[16530738,834032,16763392],"grid":[[{},{},{"objectType":"BombDrug"},{"objectType":"BombDrug"},{},{"objectType":"ColorBall"},{},{"objectType":"BombDrug"},{"objectType":"BombDrug"},{},{}],[{},{"objectType":"BombDrug"},{"objectType":"QuestionMarkBall"},{"objectType":"ColorBall"},{"objectType":"ColorBall"},{"objectType":"ColorBall"},{"objectType":"ColorBall"},{"objectType":"QuestionMarkBall"},{"objectType":"BombDrug"},{}],[{},{"objectType":"BombDrug"},{"objectType":"EmptyBall","subObjects":[{"type":"IronShell","status":0}]},{"objectType":"QuestionMarkBall"},{"objectType":"EmptyBall","subObjects":[{"type":"IronShell","status":0}]},{"objectType":"EmptyBall","subObjects":[{"type":"IronShell","status":0}]},{"objectType":"EmptyBall","subObjects":[{"type":"IronShell","status":0}]},{"objectType":"QuestionMarkBall"},{"objectType":"EmptyBall","subObjects":[{"type":"IronShell","status":0}]},{"objectType":"BombDrug"},{}],[{"objectType":"BombDrug"},{"objectType":"EmptyBall","subObjects":[{"type":"IronShell","status":0}]},{},{"objectType":"QuestionMarkBall"},{"objectType":"ColorBall"},{"objectType":"ColorBall"},{"objectType":"QuestionMarkBall"},{},{"objectType":"EmptyBall","subObjects":[{"type":"IronShell","status":0}]},{"objectType":"BombDrug"}],[{"objectType":"ColorBall"},{"objectType":"EmptyBall","subObjects":[{"type":"IronShell","status":0}]},{},{"objectType":"ColorBall"},{"objectType":"QuestionMarkBall"},{"objectType":"ColorBall"},{"objectType":"QuestionMarkBall"},{"objectType":"ColorBall"},{},{"objectType":"EmptyBall","subObjects":[{"type":"IronShell","status":0}]},{"objectType":"ColorBall"}],[{"objectType":"ColorBall"},{"objectType":"EmptyBall","subObjects":[{"type":"IronShell","status":0}]},{"objectType":"QuestionMarkBall"},{"objectType":"ColorBall"},{"objectType":"QuestionMarkBall"},{"objectType":"QuestionMarkBall"},{"objectType":"ColorBall"},{"objectType":"QuestionMarkBall"},{"objectType":"EmptyBall","subObjects":[{"type":"IronShell","status":0}]},{"objectType":"ColorBall"}],[{},{},{"objectType":"EmptyBall","subObjects":[{"type":"IronShell","status":0}]},{"objectType":"QuestionMarkBall"},{},{"objectType":"BombDrug"},{},{"objectType":"QuestionMarkBall"},{"objectType":"EmptyBall","subObjects":[{"type":"IronShell","status":0}]},{},{}],[{},{},{"objectType":"EmptyBall","subObjects":[{"type":"IronShell","status":0}]},{"objectType":"QuestionMarkBall"},{"objectType":"BombDrug"},{"objectType":"BombDrug"},{"objectType":"QuestionMarkBall"},{"objectType":"EmptyBall","subObjects":[{"type":"IronShell","status":0}]},{},{}],[{},{},{"objectType":"QuestionMarkBall"},{"objectType":"ColorBall"},{"objectType":"EmptyBall","subObjects":[{"type":"IronShell","status":0}]},{"objectType":"EmptyBall","subObjects":[{"type":"IronShell","status":0}]},{"objectType":"EmptyBall","subObjects":[{"type":"IronShell","status":0}]},{"objectType":"ColorBall"},{"objectType":"QuestionMarkBall"},{},{}],[{},{"objectType":"QuestionMarkBall"},{"objectType":"BombDrug"},{"objectType":"ColorBall"},{},{},{"objectType":"ColorBall"},{"objectType":"BombDrug"},{"objectType":"QuestionMarkBall"},{}],[{},{"objectType":"QuestionMarkBall"},{},{"objectType":"ColorBall"},{},{"objectType":"ColorBall","subObjects":[{"type":"HexagonWire","status":0}]},{},{"objectType":"ColorBall"},{},{"objectType":"QuestionMarkBall"},{}],[{},{"objectType":"QuestionMarkBall"},{"objectType":"ColorBall"},{"objectType":"ColorBall"},{"objectType":"ColorBall"},{"objectType":"ColorBall"},{"objectType":"ColorBall"},{"objectType":"ColorBall"},{"objectType":"QuestionMarkBall"},{}],[{},{},{"objectType":"QuestionMarkBall"},{"objectType":"ColorBall"},{"objectType":"EmptyBall","subObjects":[{"type":"IronShell","status":0}]},{"objectType":"EmptyBall","subObjects":[{"type":"IronShell","status":0}]},{"objectType":"EmptyBall","subObjects":[{"type":"IronShell","status":0}]},{"objectType":"ColorBall"},{"objectType":"QuestionMarkBall"},{},{}],[{},{},{},{},{},{},{},{},{},{}],[{},{},{},{},{},{},{},{},{},{},{}],[{},{"objectType":"EmptyBall","subObjects":[{"type":"IronShell","status":0}]},{"objectType":"EmptyBall","subObjects":[{"type":"IronShell","status":0}]},{"objectType":"EmptyBall","subObjects":[{"type":"IronShell","status":0}]},{},{},{"objectType":"EmptyBall","subObjects":[{"type":"IronShell","status":0}]},{"objectType":"EmptyBall","subObjects":[{"type":"IronShell","status":0}]},{"objectType":"EmptyBall","subObjects":[{"type":"IronShell","status":0}]},{}],[{},{"objectType":"ColorBall"},{"objectType":"BombDrug"},{},{"objectType":"QuestionMarkBall"},{},{"objectType":"QuestionMarkBall"},{},{"objectType":"BombDrug"},{"objectType":"ColorBall"},{}],[{"objectType":"QuestionMarkBall"},{"objectType":"BombDrug"},{"objectType":"ColorBall","subObjects":[{"type":"HexagonWire","status":0}]},{},{"objectType":"QuestionMarkBall"},{"objectType":"QuestionMarkBall"},{},{"objectType":"ColorBall","subObjects":[{"type":"HexagonWire","status":0}]},{"objectType":"BombDrug"},{"objectType":"QuestionMarkBall"}],[{"objectType":"ColorBall"},{"objectType":"QuestionMarkBall"},{"objectType":"ColorBall"},{"objectType":"ColorBall"},{"objectType":"ColorBall"},{"objectType":"ColorBall","subObjects":[{"type":"HexagonWire","status":0}]},{"objectType":"ColorBall"},{"objectType":"ColorBall"},{"objectType":"ColorBall"},{"objectType":"QuestionMarkBall"},{"objectType":"ColorBall"}],[{"objectType":"ColorBall"},{"objectType":"EmptyBall","subObjects":[{"type":"IronShell","status":0}]},{"objectType":"EmptyBall","subObjects":[{"type":"IronShell","status":0}]},{"objectType":"EmptyBall","subObjects":[{"type":"IronShell","status":0}]},{"objectType":"ColorBall"},{"objectType":"ColorBall"},{"objectType":"EmptyBall","subObjects":[{"type":"IronShell","status":0}]},{"objectType":"EmptyBall","subObjects":[{"type":"IronShell","status":0}]},{"objectType":"EmptyBall","subObjects":[{"type":"IronShell","status":0}]},{"objectType":"ColorBall"}],[{"objectType":"ColorBall"},{"objectType":"ColorBall"},{},{},{},{"objectType":"ColorBall"},{},{},{},{"objectType":"ColorBall"},{"objectType":"ColorBall"}],[{"objectType":"ColorBall"},{"objectType":"ColorBall"},{"objectType":"QuestionMarkBall"},{"objectType":"BombDrug"},{"objectType":"ColorBall"},{"objectType":"ColorBall"},{"objectType":"BombDrug"},{"objectType":"QuestionMarkBall"},{"objectType":"ColorBall"},{"objectType":"ColorBall"}],[{"objectType":"ColorBall"},{"objectType":"ColorBall"},{},{"objectType":"QuestionMarkBall"},{"objectType":"EmptyBall","subObjects":[{"type":"IronShell","status":0}]},{"objectType":"EmptyBall","subObjects":[{"type":"IronShell","status":0}]},{"objectType":"EmptyBall","subObjects":[{"type":"IronShell","status":0}]},{"objectType":"QuestionMarkBall"},{},{"objectType":"ColorBall"},{"objectType":"ColorBall"}],[{"objectType":"ColorBall"},{},{},{"objectType":"QuestionMarkBall"},{"objectType":"ColorBall"},{"objectType":"ColorBall"},{"objectType":"QuestionMarkBall"},{},{},{"objectType":"ColorBall"}],[{"objectType":"ColorBall"},{"objectType":"ColorBall"},{},{},{},{"objectType":"ColorBall"},{},{},{},{"objectType":"ColorBall"},{"objectType":"ColorBall"}],[{"objectType":"ColorBall"},{"objectType":"ColorBall"},{"objectType":"QuestionMarkBall"},{"objectType":"BombDrug"},{"objectType":"ColorBall"},{"objectType":"ColorBall"},{"objectType":"BombDrug"},{"objectType":"QuestionMarkBall"},{"objectType":"ColorBall"},{"objectType":"ColorBall"}],[{"objectType":"ColorBall"},{"objectType":"ColorBall"},{},{"objectType":"QuestionMarkBall"},{"objectType":"EmptyBall","subObjects":[{"type":"IronShell","status":0}]},{"objectType":"EmptyBall","subObjects":[{"type":"IronShell","status":0}]},{"objectType":"EmptyBall","subObjects":[{"type":"IronShell","status":0}]},{"objectType":"QuestionMarkBall"},{},{"objectType":"ColorBall"},{"objectType":"ColorBall"}],[{"objectType":"ColorBall"},{},{},{"objectType":"QuestionMarkBall"},{"objectType":"ColorBall"},{"objectType":"ColorBall"},{"objectType":"QuestionMarkBall"},{},{},{"objectType":"ColorBall"}],[{"objectType":"ColorBall"},{"objectType":"ColorBall"},{},{},{},{"objectType":"ColorBall"},{},{},{},{"objectType":"ColorBall"},{"objectType":"ColorBall"}],[{"objectType":"ColorBall"},{"objectType":"ColorBall"},{"objectType":"QuestionMarkBall"},{"objectType":"BombDrug"},{"objectType":"ColorBall"},{"objectType":"ColorBall"},{"objectType":"BombDrug"},{"objectType":"QuestionMarkBall"},{"objectType":"ColorBall"},{"objectType":"ColorBall"}],[{"objectType":"ColorBall"},{"objectType":"ColorBall"},{},{"objectType":"QuestionMarkBall"},{"objectType":"EmptyBall","subObjects":[{"type":"IronShell","status":0}]},{"objectType":"EmptyBall","subObjects":[{"type":"IronShell","status":0}]},{"objectType":"EmptyBall","subObjects":[{"type":"IronShell","status":0}]},{"objectType":"QuestionMarkBall"},{},{"objectType":"ColorBall"},{"objectType":"ColorBall"}],[{"objectType":"ColorBall"},{"objectType":"QuestionMarkBall"},{},{"objectType":"QuestionMarkBall"},{"objectType":"ColorBall"},{"objectType":"ColorBall"},{"objectType":"QuestionMarkBall"},{},{"objectType":"QuestionMarkBall"},{"objectType":"ColorBall"}],[{},{"objectType":"QuestionMarkBall"},{"objectType":"BombDrug"},{},{},{},{},{},{"objectType":"BombDrug"},{"objectType":"QuestionMarkBall"},{}],[{},{"objectType":"QuestionMarkBall"},{"objectType":"BombDrug"},{"objectType":"BombDrug"},{},{},{"objectType":"BombDrug"},{"objectType":"BombDrug"},{"objectType":"QuestionMarkBall"},{}],[{},{},{"objectType":"QuestionMarkBall"},{"objectType":"ColorBall"},{"objectType":"BombDrug"},{"objectType":"ColorBall"},{"objectType":"BombDrug"},{"objectType":"ColorBall"},{"objectType":"QuestionMarkBall"},{},{}],[{},{},{"objectType":"ColorBall"},{"objectType":"QuestionMarkBall"},{"objectType":"ColorBall"},{"objectType":"ColorBall"},{"objectType":"QuestionMarkBall"},{"objectType":"ColorBall"},{},{}],[{},{},{},{"objectType":"QuestionMarkBall"},{"objectType":"ColorBall"},{"objectType":"ColorBall","subObjects":[{"type":"HexagonWire","status":0}]},{"objectType":"ColorBall"},{"objectType":"QuestionMarkBall"},{},{},{}],[{},{},{"objectType":"QuestionMarkBall"},{"objectType":"BombDrug"},{"objectType":"ColorBall"},{"objectType":"ColorBall"},{"objectType":"BombDrug"},{"objectType":"QuestionMarkBall"},{},{}],[{},{},{"objectType":"ColorBall"},{"objectType":"QuestionMarkBall"},{"objectType":"BombDrug"},{},{"objectType":"BombDrug"},{"objectType":"QuestionMarkBall"},{"objectType":"ColorBall"},{},{}],[{},{"objectType":"ColorBall"},{"objectType":"ColorBall"},{"objectType":"QuestionMarkBall"},{"objectType":"BombDrug"},{"objectType":"BombDrug"},{"objectType":"QuestionMarkBall"},{"objectType":"ColorBall"},{"objectType":"ColorBall"},{}],[{},{"objectType":"ColorBall"},{"objectType":"ColorBall"},{"objectType":"ColorBall"},{"objectType":"QuestionMarkBall"},{"objectType":"BombDrug"},{"objectType":"QuestionMarkBall"},{"objectType":"ColorBall"},{"objectType":"ColorBall"},{"objectType":"ColorBall"},{}],[{"objectType":"EmptyBall","subObjects":[{"type":"IronShell","status":0}]},{"objectType":"BombDrug"},{},{"objectType":"ColorBall"},{"objectType":"ColorBall"},{"objectType":"ColorBall"},{"objectType":"ColorBall"},{},{"objectType":"BombDrug"},{"objectType":"EmptyBall","subObjects":[{"type":"IronShell","status":0}]}],[{"objectType":"ColorBall"},{"objectType":"EmptyBall","subObjects":[{"type":"IronShell","status":0}]},{"objectType":"BombDrug"},{"objectType":"ColorBall"},{"objectType":"ColorBall"},{"objectType":"ColorBall"},{"objectType":"ColorBall"},{"objectType":"ColorBall"},{"objectType":"BombDrug"},{"objectType":"EmptyBall","subObjects":[{"type":"IronShell","status":0}]},{"objectType":"ColorBall"}],[{"objectType":"ColorBall"},{"objectType":"EmptyBall","subObjects":[{"type":"IronShell","status":0}]},{"objectType":"ColorBall"},{"objectType":"ColorBall"},{"objectType":"ColorBall"},{"objectType":"ColorBall"},{"objectType":"ColorBall"},{"objectType":"ColorBall"},{"objectType":"EmptyBall","subObjects":[{"type":"IronShell","status":0}]},{"objectType":"ColorBall"}],[{},{},{},{},{"objectType":"QuestionMarkBall"},{"objectType":"BombDrug"},{"objectType":"QuestionMarkBall"},{},{},{},{}],[{},{},{"objectType":"ColorBall"},{"objectType":"ColorBall"},{},{},{"objectType":"ColorBall"},{"objectType":"ColorBall"},{},{}],[{},{},{},{"objectType":"ColorBall"},{"objectType":"BombDrug"},{"objectType":"ColorBall","subObjects":[{"type":"HexagonWire","status":0}]},{"objectType":"BombDrug"},{"objectType":"ColorBall"},{},{},{}],[{},{},{"objectType":"ColorBall","color":16530738},{"objectType":"ColorBall"},{"objectType":"ColorBall"},{"objectType":"ColorBall"},{"objectType":"ColorBall"},{"objectType":"ColorBall","color":834032},{},{}],[{},{},{"objectType":"ColorBall","color":16530738},{"objectType":"BombDrug"},{"objectType":"EmptyBall","subObjects":[{"type":"IronShell","status":0}]},{"objectType":"EmptyBall","subObjects":[{"type":"IronShell","status":0}]},{"objectType":"EmptyBall","subObjects":[{"type":"IronShell","status":0}]},{"objectType":"BombDrug"},{"objectType":"ColorBall","color":834032},{},{}],[{},{"objectType":"ColorBall","color":16530738},{"objectType":"ColorBall","color":16763392},{"objectType":"ColorBall","color":16763392},{"objectType":"ColorBall"},{"objectType":"ColorBall"},{"objectType":"ColorBall","color":16763392},{"objectType":"ColorBall","color":16763392},{"objectType":"ColorBall","color":834032},{}],[{},{},{},{},{},{"objectType":"ColorBall"},{},{},{},{},{}]],"colorButtonOverlay":"orange"}