{"isHard":false,"numberBullets":30,"bulletsColor":[16530738,834032],"starsTarget":[4000,11000,17000],"missionType":"CollectBubbles","colors":[158691,16763392,834032,16530738],"grid":[[{"objectType":"ColorBall","color":158691},{"objectType":"Stone"},{"objectType":"ColorBall","color":16763392},{},{"objectType":"ColorBall","color":834032},{"objectType":"Stone"},{"objectType":"ColorBall","color":16530738},{},{"objectType":"ColorBall","color":158691},{"objectType":"Stone"},{"objectType":"ColorBall","color":16763392}],[{"objectType":"ColorBall","color":158691},{"objectType":"ColorBall","color":16763392},{},{"objectType":"ColorBall","color":16530738},{"objectType":"ColorBall","color":834032},{"objectType":"ThunderBall","color":16530738},{"objectType":"ColorBall","color":834032},{},{"objectType":"ColorBall","color":158691},{"objectType":"ColorBall","color":16763392}],[{},{"objectType":"ColorBall","color":16763392},{},{"objectType":"ColorBall","color":16530738},{"objectType":"Stone"},{},{"objectType":"Stone"},{"objectType":"ColorBall","color":834032},{},{"objectType":"ColorBall","color":158691},{}],[{"objectType":"ThunderBall","color":16763392},{"objectType":"ColorBall","color":158691},{"objectType":"ColorBall","color":16530738},{},{"objectType":"ColorBall","color":16763392},{"objectType":"ColorBall","color":16763392},{},{"objectType":"ColorBall","color":834032},{"objectType":"ColorBall","color":16763392},{"objectType":"ThunderBall","color":158691}],[{},{"objectType":"Stone"},{"objectType":"ColorBall","color":16530738},{},{},{"objectType":"Stone"},{},{},{"objectType":"ColorBall","color":834032},{"objectType":"Stone"},{}],[{},{"objectType":"ColorBall","color":16530738},{"objectType":"Stone"},{},{},{},{},{"objectType":"Stone"},{"objectType":"ColorBall","color":834032},{}],[{},{"objectType":"ColorBall","color":16530738},{},{"objectType":"ColorBall","color":16763392},{"objectType":"Stone"},{},{"objectType":"Stone"},{"objectType":"ColorBall","color":16763392},{},{"objectType":"ColorBall","color":834032},{}],[{"objectType":"ColorBall","color":16530738},{},{"objectType":"ThunderBall","color":16763392},{"objectType":"ColorBall","color":16530738},{"objectType":"ColorBall","color":16530738},{"objectType":"ColorBall","color":16530738},{"objectType":"ColorBall","color":16530738},{"objectType":"ColorBall","color":834032},{},{"objectType":"ColorBall","color":834032}],[{"objectType":"ColorBall","color":16530738},{},{},{"objectType":"ColorBall","color":16763392},{"objectType":"ColorBall","color":16530738},{"objectType":"ColorBall","color":16530738},{"objectType":"ColorBall","color":16530738},{"objectType":"ColorBall","color":834032},{},{},{"objectType":"ColorBall","color":834032}],[{"objectType":"Stone"},{},{"objectType":"Stone"},{"objectType":"Stone"},{"objectType":"ColorBall","color":834032},{"objectType":"ColorBall","color":834032},{"objectType":"Stone"},{"objectType":"Stone"},{},{"objectType":"Stone"}],[{},{},{},{"objectType":"ColorBall","color":16763392},{"objectType":"ColorBall","color":16763392},{"objectType":"ColorBall","color":16763392},{"objectType":"ColorBall","color":16763392},{"objectType":"ColorBall","color":16763392},{},{},{}],[{},{},{"objectType":"ColorBall","color":16530738},{"objectType":"Stone"},{"objectType":"Stone"},{"objectType":"Stone"},{"objectType":"Stone"},{"objectType":"ColorBall","color":158691},{},{}],[{},{},{"objectType":"ColorBall","color":16530738},{"objectType":"ColorBall","color":16530738},{"objectType":"ColorBall","color":16530738},{"objectType":"ColorBall","color":16763392},{"objectType":"ColorBall","color":158691},{"objectType":"ColorBall","color":158691},{"objectType":"ThunderBall","color":158691},{},{}],[{},{"objectType":"ColorBall","color":16530738},{"objectType":"Stone"},{"objectType":"ColorBall","color":834032},{"objectType":"ColorBall","color":834032},{"objectType":"ColorBall","color":16530738},{"objectType":"ColorBall","color":16530738},{"objectType":"Stone"},{"objectType":"ColorBall","color":158691},{}],[{},{"objectType":"Stone"},{"objectType":"Stone"},{"objectType":"ColorBall","color":16763392},{"objectType":"ColorBall","color":158691},{"objectType":"ColorBall","color":158691},{"objectType":"ColorBall","color":158691},{"objectType":"ColorBall","color":834032},{"objectType":"Stone"},{"objectType":"Stone"},{}],[{"objectType":"ColorBall","color":16530738},{"objectType":"ColorBall","color":834032},{"objectType":"Stone"},{},{},{},{},{"objectType":"Stone"},{"objectType":"ColorBall","color":16530738},{"objectType":"ColorBall","color":16763392}],[{"objectType":"ColorBall","color":16530738},{"objectType":"ColorBall","color":834032},{"objectType":"ColorBall","color":834032},{"objectType":"Stone"},{},{},{},{"objectType":"Stone"},{"objectType":"ColorBall","color":16530738},{"objectType":"ColorBall","color":16763392},{"objectType":"ColorBall","color":16763392}],[{"objectType":"ColorBall","color":834032},{"objectType":"ColorBall","color":834032},{"objectType":"ThunderBall","color":16530738},{"objectType":"Stone"},{"objectType":"ColorBall","color":158691},{"objectType":"ColorBall","color":158691},{"objectType":"Stone"},{"objectType":"ColorBall","color":834032},{"objectType":"ColorBall","color":16763392},{"objectType":"ColorBall","color":158691}],[{"objectType":"ColorBall","color":834032},{"objectType":"ColorBall","color":834032},{"objectType":"ColorBall","color":16530738},{"objectType":"ColorBall","color":16530738},{"objectType":"ColorBall","color":158691},{"objectType":"ColorBall","color":158691},{"objectType":"ColorBall","color":158691},{"objectType":"ColorBall","color":834032},{"objectType":"ThunderBall","color":834032},{"objectType":"ColorBall","color":158691},{"objectType":"ColorBall","color":158691}],[{"objectType":"ColorBall","color":834032},{"objectType":"ColorBall","color":16530738},{"objectType":"Stone"},{"objectType":"ColorBall","color":16530738},{"objectType":"Stone"},{"objectType":"Stone"},{"objectType":"ColorBall","color":834032},{"objectType":"Stone"},{"objectType":"ColorBall","color":16763392},{"objectType":"ColorBall","color":158691}],[{},{},{"objectType":"Stone"},{"objectType":"ColorBall","color":16530738},{},{},{},{"objectType":"ColorBall","color":834032},{"objectType":"Stone"},{},{}],[{},{"objectType":"Stone"},{"objectType":"ColorBall","color":16530738},{},{"objectType":"Stone"},{"objectType":"Stone"},{},{"objectType":"ColorBall","color":834032},{"objectType":"Stone"},{}],[{},{},{"objectType":"ColorBall","color":16530738},{"objectType":"ColorBall","color":158691},{"objectType":"Stone"},{},{"objectType":"Stone"},{"objectType":"ColorBall","color":16763392},{"objectType":"ColorBall","color":834032},{},{}],[{},{},{"objectType":"ColorBall","color":158691},{},{"objectType":"Stone"},{"objectType":"Stone"},{},{"objectType":"ColorBall","color":16763392},{},{}],[{},{},{"objectType":"ColorBall","color":158691},{},{},{},{},{},{"objectType":"ColorBall","color":16763392},{},{}],[{},{},{"objectType":"ColorBall"},{"objectType":"ColorBall"},{"objectType":"ColorBall"},{"objectType":"ColorBall"},{"objectType":"ColorBall"},{"objectType":"ColorBall"},{},{}]],"colorButtonOverlay":"green"}