{"isHard":false,"numberBullets":22,"bulletsColor":[],"bulletItems":{"BombBulletItem":0,"ElectricBulletBallItem":0,"RainbowBulletBallItem":0,"RocketBulletItem":0},"starsTarget":[6000,15000,23000],"missionType":"CollectGems","colors":[57396,16763392,16711935,158691],"grid":[[{},{"objectType":"EarthenPot"},{"objectType":"EarthenPot"},{"objectType":"EarthenPot"},{"objectType":"EarthenPot"},{"objectType":"EarthenPot"},{},{},{},{},{}],[{"objectType":"EarthenPot"},{"objectType":"WhiteBall"},{"objectType":"WhiteBall"},{"objectType":"WhiteBall"},{"objectType":"WhiteBall"},{"objectType":"EarthenPot"},{},{},{},{}],[{"objectType":"EarthenPot"},{"objectType":"WhiteBall"},{"objectType":"ThunderBall"},{"objectType":"ColorBall"},{"objectType":"GemBall"},{"objectType":"WhiteBall"},{"objectType":"EarthenPot"},{},{},{},{}],[{"objectType":"WhiteBall"},{"objectType":"ColorBall"},{"objectType":"ColorBall"},{"objectType":"ColorBall"},{"objectType":"ColorBall"},{"objectType":"WhiteBall"},{"objectType":"EarthenPot"},{},{},{}],[{"objectType":"WhiteBall"},{"objectType":"ColorBall"},{"objectType":"ColorBall"},{"objectType":"GemBall"},{"objectType":"ColorBall"},{"objectType":"ColorBall"},{"objectType":"WhiteBall"},{"objectType":"EarthenPot"},{},{},{}],[{"objectType":"WhiteBall"},{"objectType":"ColorBall"},{"objectType":"ColorBall"},{"objectType":"ColorBall"},{"objectType":"ColorBall"},{"objectType":"WhiteBall"},{"objectType":"EarthenPot"},{},{},{}],[{"objectType":"EarthenPot"},{"objectType":"WhiteBall"},{"objectType":"GemBall"},{"objectType":"ColorBall"},{"objectType":"ThunderBall"},{"objectType":"WhiteBall"},{"objectType":"EarthenPot"},{},{},{},{}],[{"objectType":"EarthenPot"},{"objectType":"WhiteBall"},{"objectType":"WhiteBall"},{"objectType":"WhiteBall"},{"objectType":"WhiteBall"},{"objectType":"ColorBall"},{"objectType":"ColorBall"},{"objectType":"ColorBall"},{"objectType":"ColorBall"},{}],[{},{"objectType":"EarthenPot"},{"objectType":"EarthenPot"},{"objectType":"EarthenPot"},{"objectType":"EarthenPot"},{"objectType":"ColorBall"},{"objectType":"RandomDirectionElectricBall","status":1},{"objectType":"ColorBall"},{"objectType":"RandomDirectionElectricBall","status":1},{"objectType":"ColorBall"},{}],[{},{},{},{},{"objectType":"ColorBall"},{"objectType":"ColorBall"},{"objectType":"ColorBall"},{"objectType":"ColorBall"},{"objectType":"ColorBall"},{"objectType":"ColorBall"}],[{},{},{},{},{"objectType":"ColorBall"},{"objectType":"RandomDirectionElectricBall","status":1},{"objectType":"ColorBall"},{"objectType":"GemBall"},{"objectType":"ColorBall"},{"objectType":"RandomDirectionElectricBall","status":1},{"objectType":"ColorBall"}],[{},{},{},{},{"objectType":"ColorBall"},{"objectType":"ColorBall"},{"objectType":"ColorBall"},{"objectType":"ColorBall"},{"objectType":"ColorBall"},{"objectType":"ColorBall"}],[{},{},{},{},{},{"objectType":"ColorBall"},{"objectType":"RandomDirectionElectricBall","status":1},{"objectType":"ColorBall"},{"objectType":"RandomDirectionElectricBall","status":1},{"objectType":"ColorBall"},{}],[{},{},{},{},{},{"objectType":"ColorBall"},{"objectType":"ColorBall"},{"objectType":"ColorBall"},{"objectType":"ColorBall"},{}],[{},{"objectType":"ColorBall"},{"objectType":"ColorBall"},{"objectType":"ColorBall"},{"objectType":"ColorBall"},{"objectType":"ColorBall"},{"objectType":"ColorBall"},{"objectType":"ColorBall"},{"objectType":"ColorBall"},{"objectType":"ColorBall"},{}],[{"objectType":"ThunderBall"},{"objectType":"WhiteBall"},{"objectType":"ThunderBall"},{"objectType":"WhiteBall"},{"objectType":"ThunderBall"},{"objectType":"WhiteBall"},{"objectType":"ThunderBall"},{"objectType":"WhiteBall"},{"objectType":"ThunderBall"},{"objectType":"WhiteBall"}],[{},{"objectType":"ColorBall"},{"objectType":"ColorBall"},{"objectType":"ColorBall"},{"objectType":"ColorBall"},{"objectType":"ColorBall"},{"objectType":"ColorBall"},{"objectType":"ColorBall"},{"objectType":"ColorBall"},{"objectType":"ColorBall"},{}],[{},{"objectType":"WhiteBall"},{"objectType":"WhiteBall"},{"objectType":"WhiteBall"},{"objectType":"WhiteBall"},{},{},{},{},{}],[{},{"objectType":"WhiteBall"},{"objectType":"GemBall"},{"objectType":"ColorBall"},{"objectType":"ThunderBall"},{"objectType":"WhiteBall"},{},{},{},{},{}],[{"objectType":"WhiteBall"},{"objectType":"ColorBall"},{"objectType":"ColorBall"},{"objectType":"ColorBall"},{"objectType":"ColorBall"},{"objectType":"WhiteBall"},{},{},{},{}],[{"objectType":"WhiteBall"},{"objectType":"ColorBall"},{"objectType":"ColorBall"},{"objectType":"RandomDirectionElectricBall","status":2},{"objectType":"ColorBall"},{"objectType":"ColorBall"},{"objectType":"WhiteBall"},{},{},{},{}],[{"objectType":"WhiteBall"},{"objectType":"ColorBall"},{"objectType":"ColorBall"},{"objectType":"ColorBall"},{"objectType":"ColorBall"},{"objectType":"WhiteBall"},{},{},{},{}],[{},{"objectType":"WhiteBall"},{"objectType":"ThunderBall"},{"objectType":"ColorBall"},{"objectType":"GemBall"},{"objectType":"WhiteBall"},{},{},{},{},{}],[{},{"objectType":"WhiteBall"},{"objectType":"WhiteBall"},{"objectType":"WhiteBall"},{"objectType":"WhiteBall"},{"objectType":"ColorBall","color":57396},{"objectType":"ColorBall","color":57396},{"objectType":"ColorBall","color":16763392},{"objectType":"ColorBall","color":16763392},{}],[{},{},{},{},{},{"objectType":"ColorBall","color":16711935},{"objectType":"RandomDirectionElectricBall","status":1},{"objectType":"ColorBall","color":57396},{"objectType":"RandomDirectionElectricBall","status":1},{"objectType":"ColorBall","color":16763392},{}],[{},{},{},{},{"objectType":"ColorBall","color":57396},{"objectType":"ColorBall","color":16711935},{"objectType":"ColorBall","color":158691},{"objectType":"ColorBall","color":57396},{"objectType":"ColorBall","color":16763392},{"objectType":"ColorBall","color":16763392}],[{},{},{},{},{"objectType":"ColorBall","color":158691},{"objectType":"RandomDirectionElectricBall","status":1},{"objectType":"ColorBall","color":16711935},{"objectType":"GemBall","color":158691},{"objectType":"ColorBall","color":16763392},{"objectType":"RandomDirectionElectricBall","status":1},{"objectType":"ColorBall","color":158691}],[{},{},{},{},{"objectType":"ColorBall","color":158691},{"objectType":"ColorBall","color":16763392},{"objectType":"ColorBall","color":16711935},{"objectType":"ColorBall","color":158691},{"objectType":"ColorBall","color":16763392},{"objectType":"ColorBall","color":158691}],[{},{},{},{},{},{"objectType":"ColorBall","color":158691},{"objectType":"RandomDirectionElectricBall","status":1},{"objectType":"ColorBall","color":16711935},{"objectType":"RandomDirectionElectricBall","status":1},{"objectType":"ColorBall","color":158691},{}],[{},{},{},{},{},{"objectType":"ColorBall","color":16763392},{"objectType":"ColorBall","color":16763392},{"objectType":"ColorBall","color":57396},{"objectType":"ColorBall","color":57396},{}]],"colorButtonOverlay":"orange","treasure":{"ElectricBulletBallItem":1}}