{"isHard":false,"numberBullets":35,"bulletsColor":[],"bulletItems":{"BombBulletItem":0,"ElectricBulletBallItem":0,"RainbowBulletBallItem":0,"RocketBulletItem":0},"starsTarget":[2500,8000,18000],"missionType":"CollectGems","colors":[16711935,16763392,57396],"grid":[[{},{},{},{"objectType":"ColorBall"},{"objectType":"ColorBall"},{"objectType":"ColorBall"},{"objectType":"ColorBall"},{"objectType":"ColorBall"},{},{},{}],[{},{"objectType":"ColorBall"},{"objectType":"ColorBall"},{"objectType":"ColorBall"},{"objectType":"ColorBall"},{"objectType":"ThunderBall"},{"objectType":"ColorBall"},{"objectType":"ColorBall"},{"objectType":"ColorBall"},{}],[{},{"objectType":"ColorBall"},{"objectType":"ColorBall"},{"objectType":"ColorBall"},{},{"objectType":"ColorBall"},{},{"objectType":"ColorBall"},{"objectType":"ColorBall","subObjects":[{"type":"HexagonWire","status":0}]},{"objectType":"ColorBall"},{}],[{"objectType":"ColorBall"},{"objectType":"ColorBall"},{},{},{"objectType":"ColorBall"},{},{},{},{"objectType":"ColorBall"},{"objectType":"ColorBall"}],[{"objectType":"ColorBall"},{"objectType":"ColorBall"},{},{"objectType":"SwitchBlackHole","status":1},{"objectType":"GemBall","color":16711935},{"objectType":"ColorBall","subObjects":[{"type":"HexagonWire","status":0}]},{"objectType":"GemBall","color":16763392},{"objectType":"SwitchBlackHole","status":1},{},{"objectType":"ColorBall"},{"objectType":"ColorBall"}],[{"objectType":"ColorBall"},{"objectType":"ColorBall"},{"objectType":"SwitchBlackHole"},{"objectType":"GemBall","color":57396},{"objectType":"SwitchBlackHole","status":1},{"objectType":"SwitchBlackHole","status":1},{"objectType":"GemBall","color":16711935},{"objectType":"SwitchBlackHole"},{"objectType":"ColorBall","color":16711935},{"objectType":"ColorBall"}],[{"objectType":"SwitchBlackHole"},{"objectType":"ColorBall"},{},{"objectType":"SwitchBlackHole","status":1},{"objectType":"GemBall","color":16763392},{"objectType":"ColorBall","subObjects":[{"type":"HexagonWire","status":0}]},{"objectType":"GemBall","color":57396},{"objectType":"SwitchBlackHole","status":1},{},{"objectType":"ColorBall","color":16711935},{"objectType":"SwitchBlackHole"}],[{"objectType":"ColorBall"},{"objectType":"ColorBall"},{},{},{},{"objectType":"ColorBall"},{},{},{"objectType":"ColorBall","color":57396},{"objectType":"ColorBall"}],[{},{"objectType":"SwitchBlackHole","status":1},{"objectType":"ColorBall","subObjects":[{"type":"HexagonWire","status":0}]},{"objectType":"ColorBall"},{"objectType":"SwitchBlackHole"},{"objectType":"ColorBall"},{"objectType":"SwitchBlackHole"},{"objectType":"ColorBall","color":16763392},{"objectType":"ColorBall","color":57396},{"objectType":"SwitchBlackHole","status":1},{}],[{},{"objectType":"ColorBall"},{"objectType":"ColorBall"},{"objectType":"ColorBall"},{"objectType":"ThunderBall"},{"objectType":"ColorBall"},{"objectType":"ColorBall","color":16763392},{"objectType":"ColorBall"},{"objectType":"ColorBall"},{}],[{},{},{},{"objectType":"SwitchBlackHole"},{"objectType":"SwitchBlackHole","status":1},{"objectType":"ColorBall"},{"objectType":"SwitchBlackHole","status":1},{"objectType":"SwitchBlackHole"},{},{},{}],[{},{},{},{},{},{},{},{},{},{}],[{},{},{},{},{},{},{},{},{},{},{}],[{},{},{},{},{},{},{},{},{},{}],[{},{},{},{},{},{},{},{},{},{},{}],[{},{},{},{},{},{},{},{},{},{}],[{},{},{},{},{},{},{},{},{},{},{}],[{},{},{},{},{},{},{},{},{},{}],[{},{},{},{},{},{},{},{},{},{},{}],[{},{"objectType":"ColorBall"},{"objectType":"ColorBall"},{"objectType":"ColorBall"},{"objectType":"ColorBall"},{"objectType":"ColorBall"},{"objectType":"ColorBall"},{"objectType":"ColorBall"},{"objectType":"ColorBall"},{}],[{},{"objectType":"ColorBall"},{"objectType":"ColorBall","subObjects":[{"type":"HexagonWire","status":0}]},{"objectType":"ColorBall"},{"objectType":"SwitchBlackHole","status":1},{"objectType":"SwitchBlackHole","status":1},{"objectType":"SwitchBlackHole","status":1},{"objectType":"ColorBall"},{"objectType":"ColorBall","subObjects":[{"type":"HexagonWire","status":0}]},{"objectType":"ColorBall"},{}],[{},{"objectType":"SwitchBlackHole"},{"objectType":"ColorBall"},{"objectType":"ThunderBall"},{},{},{"objectType":"ThunderBall"},{"objectType":"ColorBall"},{"objectType":"SwitchBlackHole"},{}],[{},{},{"objectType":"ColorBall"},{"objectType":"SwitchBlackHole"},{},{"objectType":"GemBall","color":16763392},{},{"objectType":"SwitchBlackHole","status":1},{"objectType":"ColorBall"},{},{}],[{},{},{"objectType":"ColorBall"},{"objectType":"SwitchBlackHole","status":1},{"objectType":"GemBall","color":16711935},{"objectType":"GemBall","color":16711935},{"objectType":"SwitchBlackHole"},{"objectType":"ColorBall"},{},{}],[{},{},{},{"objectType":"ColorBall"},{"objectType":"SwitchBlackHole"},{},{"objectType":"SwitchBlackHole","status":1},{"objectType":"ColorBall"},{},{},{}],[{},{},{},{"objectType":"ColorBall"},{"objectType":"ColorBall"},{"objectType":"ColorBall"},{"objectType":"ColorBall"},{},{},{}],[{},{},{},{},{"objectType":"ColorBall"},{"objectType":"ColorBall","subObjects":[{"type":"HexagonWire","status":0}]},{"objectType":"ColorBall"},{},{},{},{}],[{},{},{},{},{"objectType":"ColorBall"},{"objectType":"ColorBall"},{},{},{},{}],[{},{},{},{},{},{"objectType":"SwitchBlackHole"},{},{},{},{},{}],[{},{},{},{},{},{},{},{},{},{}],[{},{},{},{},{},{},{},{},{},{},{}],[{},{},{},{},{},{},{},{},{},{}],[{},{},{},{},{},{},{},{},{},{},{}],[{},{},{},{},{},{},{},{},{},{}],[{},{},{},{},{},{},{},{},{},{},{}],[{},{},{},{},{},{},{},{},{},{}],[{"objectType":"ColorBall","color":57396},{"objectType":"ColorBall"},{"objectType":"ColorBall"},{"objectType":"ColorBall"},{"objectType":"ColorBall","color":16711935},{"objectType":"ColorBall","color":16711935,"subObjects":[{"type":"HexagonWire","status":0}]},{"objectType":"ColorBall","color":16711935},{"objectType":"ColorBall"},{"objectType":"ColorBall"},{"objectType":"ColorBall","color":16763392},{"objectType":"ColorBall"}],[{"objectType":"ColorBall","color":57396},{},{},{"objectType":"SwitchBlackHole"},{"objectType":"ColorBall","color":16711935},{"objectType":"ColorBall","color":16711935},{"objectType":"SwitchBlackHole"},{},{},{"objectType":"ColorBall","color":16763392}],[{"objectType":"ColorBall","color":57396},{"objectType":"ColorBall","color":57396},{},{"objectType":"ColorBall"},{"objectType":"ColorBall"},{},{"objectType":"ColorBall"},{"objectType":"ThunderBall"},{},{"objectType":"ColorBall","color":16763392},{"objectType":"ColorBall","color":16763392}],[{"objectType":"SwitchBlackHole","status":1},{"objectType":"ColorBall","color":57396,"subObjects":[{"type":"HexagonWire","status":0}]},{"objectType":"SwitchBlackHole","status":1},{"objectType":"ColorBall"},{"objectType":"GemBall","color":57396},{"objectType":"GemBall","color":57396},{"objectType":"ColorBall"},{"objectType":"SwitchBlackHole","status":1},{"objectType":"ColorBall","color":16763392,"subObjects":[{"type":"HexagonWire","status":0}]},{"objectType":"SwitchBlackHole","status":1}],[{"objectType":"ColorBall"},{"objectType":"ColorBall"},{},{"objectType":"ThunderBall"},{"objectType":"ColorBall"},{},{"objectType":"ColorBall"},{"objectType":"ColorBall"},{},{"objectType":"ColorBall"},{"objectType":"ColorBall"}],[{"objectType":"ColorBall"},{},{},{"objectType":"SwitchBlackHole"},{"objectType":"ColorBall"},{"objectType":"ColorBall"},{"objectType":"SwitchBlackHole"},{},{},{"objectType":"ColorBall"}],[{"objectType":"ColorBall"},{"objectType":"ColorBall"},{"objectType":"ColorBall"},{"objectType":"ColorBall"},{"objectType":"ColorBall"},{"objectType":"ColorBall"},{"objectType":"ColorBall"},{"objectType":"ColorBall"},{"objectType":"ColorBall"},{"objectType":"ColorBall"},{"objectType":"ColorBall"}]],"colorButtonOverlay":"purple","treasure":{"Coin":15}}