{"isHard":true,"numberBullets":37,"bulletsColor":[],"bulletItems":{"BombBulletItem":0,"ElectricBulletBallItem":0,"RainbowBulletBallItem":0,"RocketBulletItem":0},"starsTarget":[14000,30000,56000],"missionType":"CollectBubbles","colors":[158691,16711935,834032,16763392,16530738],"grid":[[{},{},{"objectType":"ColorBall"},{"objectType":"ColorBall"},{"objectType":"ColorBall"},{"objectType":"EarthenPot"},{"objectType":"ColorBall"},{"objectType":"ColorBall"},{"objectType":"ColorBall"},{},{}],[{},{"objectType":"ColorBall"},{"objectType":"ColorBall"},{},{},{},{},{"objectType":"ColorBall"},{"objectType":"ColorBall"},{}],[{},{"objectType":"EarthenPot"},{"objectType":"ColorBall"},{"objectType":"ColorBall"},{"objectType":"ColorBall"},{},{"objectType":"ColorBall"},{"objectType":"ColorBall"},{"objectType":"ColorBall"},{"objectType":"EarthenPot"},{}],[{},{"objectType":"EarthenPot"},{"objectType":"ColorBall"},{"objectType":"ColorBall"},{"objectType":"ColorBall"},{"objectType":"ColorBall"},{"objectType":"ColorBall"},{"objectType":"ColorBall"},{"objectType":"EarthenPot"},{}],[{},{"objectType":"EarthenPot"},{"objectType":"ColorBall"},{"objectType":"ColorBall","subObjects":[{"type":"Bat","status":0},{"type":"IronShell","status":1}]},{"objectType":"ColorBall","subObjects":[{"type":"Bat","status":0},{"type":"IronShell","status":1}]},{"objectType":"ColorBall","subObjects":[{"type":"Bat","status":0},{"type":"IronShell","status":1}]},{"objectType":"ColorBall","subObjects":[{"type":"Bat","status":0},{"type":"IronShell","status":1}]},{"objectType":"ColorBall","subObjects":[{"type":"Bat","status":0},{"type":"IronShell","status":1}]},{"objectType":"ColorBall"},{"objectType":"EarthenPot"},{}],[{},{"objectType":"ColorBall"},{},{},{},{},{},{},{"objectType":"ColorBall"},{}],[{},{},{"objectType":"ColorBall"},{"objectType":"ColorBall","subObjects":[{"type":"Bat","status":0},{"type":"IronShell","status":0}]},{"objectType":"ColorBall","subObjects":[{"type":"Bat","status":0},{"type":"IronShell","status":0}]},{"objectType":"ColorBomb","subObjects":[{"type":"Bat","status":0}]},{"objectType":"ColorBall","subObjects":[{"type":"Bat","status":0},{"type":"IronShell","status":0}]},{"objectType":"ColorBall","subObjects":[{"type":"Bat","status":0},{"type":"IronShell","status":0}]},{"objectType":"ColorBall"},{},{}],[{},{"objectType":"ColorBall"},{"objectType":"ColorBall"},{"objectType":"ColorBall"},{},{},{"objectType":"ColorBall"},{"objectType":"ColorBall"},{"objectType":"ColorBall"},{}],[{"objectType":"ColorBomb","subObjects":[{"type":"Bat","status":0}]},{"objectType":"ColorBall"},{"objectType":"ColorBall"},{"objectType":"ColorBall"},{"objectType":"ColorBall"},{},{"objectType":"ColorBall"},{"objectType":"ColorBall"},{"objectType":"ColorBall"},{"objectType":"ColorBall"},{"objectType":"ColorBomb","subObjects":[{"type":"Bat","status":0}]}],[{},{},{"objectType":"ColorBall"},{"objectType":"ColorBall"},{"objectType":"ColorBall","subObjects":[{"type":"Bat","status":0},{"type":"IronShell","status":1}]},{"objectType":"ColorBall","subObjects":[{"type":"Bat","status":0},{"type":"IronShell","status":1}]},{"objectType":"ColorBall"},{"objectType":"ColorBall"},{},{}],[{},{},{"objectType":"ColorBall"},{"objectType":"EarthenPot"},{"objectType":"EarthenPot"},{},{"objectType":"EarthenPot"},{"objectType":"EarthenPot"},{"objectType":"ColorBall"},{},{}],[{},{},{"objectType":"ColorBall"},{"objectType":"ColorBall"},{"objectType":"EarthenPot"},{"objectType":"EarthenPot"},{"objectType":"ColorBall"},{"objectType":"ColorBall"},{},{}],[{},{},{"objectType":"ColorBall"},{"objectType":"ColorBall"},{"objectType":"ColorBall","subObjects":[{"type":"Bat","status":0},{"type":"IronShell","status":1}]},{"objectType":"ColorBall","subObjects":[{"type":"Bat","status":0},{"type":"IronShell","status":1}]},{"objectType":"ColorBall","subObjects":[{"type":"Bat","status":0},{"type":"IronShell","status":1}]},{"objectType":"ColorBall"},{"objectType":"ColorBall"},{},{}],[{},{"objectType":"EarthenPot"},{"objectType":"ColorBall"},{"objectType":"ColorBall"},{},{},{"objectType":"ColorBall"},{"objectType":"ColorBall"},{"objectType":"EarthenPot"},{}],[{},{"objectType":"EarthenPot"},{"objectType":"ColorBall"},{},{},{},{},{},{"objectType":"ColorBall"},{"objectType":"EarthenPot"},{}],[{},{"objectType":"EarthenPot"},{"objectType":"ColorBall"},{"objectType":"ColorBall"},{"objectType":"ColorBomb","subObjects":[{"type":"Bat","status":0}]},{"objectType":"ColorBomb","subObjects":[{"type":"Bat","status":0}]},{"objectType":"ColorBall"},{"objectType":"ColorBall"},{"objectType":"EarthenPot"},{}],[{"objectType":"ColorBall"},{"objectType":"ColorBall"},{"objectType":"ColorBall"},{"objectType":"ColorBall"},{"objectType":"ColorBall"},{},{"objectType":"ColorBall"},{"objectType":"ColorBall"},{"objectType":"ColorBall"},{"objectType":"ColorBall"},{"objectType":"ColorBall"}],[{},{"objectType":"ColorBall"},{"objectType":"ColorBall"},{"objectType":"ColorBall"},{"objectType":"ColorBall"},{"objectType":"ColorBall"},{"objectType":"ColorBall"},{"objectType":"ColorBall"},{"objectType":"ColorBall"},{}],[{},{},{"objectType":"ColorBall"},{"objectType":"ColorBall","subObjects":[{"type":"Bat","status":0},{"type":"IronShell","status":0}]},{"objectType":"ColorBall","subObjects":[{"type":"Bat","status":0},{"type":"IronShell","status":0}]},{},{"objectType":"ColorBall","subObjects":[{"type":"Bat","status":0},{"type":"IronShell","status":0}]},{"objectType":"ColorBall","subObjects":[{"type":"Bat","status":0},{"type":"IronShell","status":0}]},{"objectType":"ColorBall"},{},{}],[{},{"objectType":"ColorBall"},{"objectType":"ColorBall","subObjects":[{"type":"Bat","status":0},{"type":"IronShell","status":0}]},{"objectType":"EarthenPot"},{},{},{"objectType":"EarthenPot"},{"objectType":"ColorBall","subObjects":[{"type":"Bat","status":0},{"type":"IronShell","status":0}]},{"objectType":"ColorBall"},{}],[{},{},{"objectType":"ColorBall"},{"objectType":"ColorBall","subObjects":[{"type":"Bat","status":0},{"type":"IronShell","status":0}]},{"objectType":"ColorBall","subObjects":[{"type":"Bat","status":0},{"type":"IronShell","status":0}]},{},{"objectType":"ColorBall","subObjects":[{"type":"Bat","status":0},{"type":"IronShell","status":0}]},{"objectType":"ColorBall","subObjects":[{"type":"Bat","status":0},{"type":"IronShell","status":0}]},{"objectType":"ColorBall"},{},{}],[{},{},{"objectType":"ColorBall"},{"objectType":"ColorBall"},{"objectType":"ColorBall"},{"objectType":"ColorBall"},{"objectType":"ColorBall"},{"objectType":"ColorBall"},{},{}],[{},{},{"objectType":"ColorBall"},{"objectType":"ColorBall"},{"objectType":"ColorBall"},{"objectType":"ColorBall"},{"objectType":"ColorBall"},{"objectType":"ColorBall"},{"objectType":"ColorBall"},{},{}],[{},{"objectType":"ColorBall"},{"objectType":"EarthenPot"},{"objectType":"EarthenPot"},{},{},{"objectType":"EarthenPot"},{"objectType":"EarthenPot"},{"objectType":"ColorBall"},{}],[{},{},{"objectType":"ColorBall"},{"objectType":"ColorBall"},{"objectType":"ColorBall","subObjects":[{"type":"Bat","status":0},{"type":"IronShell","status":1}]},{"objectType":"ColorBomb","subObjects":[{"type":"Bat","status":0}]},{"objectType":"ColorBall","subObjects":[{"type":"Bat","status":0},{"type":"IronShell","status":1}]},{"objectType":"ColorBall"},{"objectType":"ColorBall"},{},{}],[{},{"objectType":"ColorBall"},{"objectType":"ColorBall"},{"objectType":"ColorBall","subObjects":[{"type":"Bat","status":0},{"type":"IronShell","status":1}]},{},{},{"objectType":"ColorBall","subObjects":[{"type":"Bat","status":0},{"type":"IronShell","status":1}]},{"objectType":"ColorBall"},{"objectType":"ColorBall"},{}],[{"objectType":"ColorBomb","subObjects":[{"type":"Bat","status":0}]},{"objectType":"ColorBall"},{"objectType":"ColorBall"},{"objectType":"ColorBall"},{"objectType":"ColorBall"},{},{"objectType":"ColorBall"},{"objectType":"ColorBall"},{"objectType":"ColorBall"},{"objectType":"ColorBall"},{"objectType":"ColorBomb","subObjects":[{"type":"Bat","status":0}]}],[{},{},{"objectType":"ColorBall"},{"objectType":"ColorBall"},{},{},{"objectType":"ColorBall"},{"objectType":"ColorBall"},{},{}],[{},{},{"objectType":"ColorBall"},{"objectType":"EarthenPot"},{},{},{},{"objectType":"EarthenPot"},{"objectType":"ColorBall"},{},{}],[{},{},{"objectType":"ColorBall"},{"objectType":"ColorBall"},{},{},{"objectType":"ColorBall"},{"objectType":"ColorBall"},{},{}],[{},{"objectType":"ColorBall"},{"objectType":"ColorBall"},{"objectType":"ColorBall"},{"objectType":"ColorBall"},{},{"objectType":"ColorBall"},{"objectType":"ColorBall"},{"objectType":"ColorBall"},{"objectType":"ColorBall"},{}],[{},{"objectType":"ColorBall"},{"objectType":"ColorBall","subObjects":[{"type":"Bat","status":0},{"type":"IronShell","status":1}]},{"objectType":"ColorBall"},{},{},{"objectType":"ColorBall"},{"objectType":"ColorBall","subObjects":[{"type":"Bat","status":0},{"type":"IronShell","status":1}]},{"objectType":"ColorBall"},{}],[{"objectType":"ColorBomb","subObjects":[{"type":"Bat","status":0}]},{"objectType":"ColorBall"},{"objectType":"ColorBall","subObjects":[{"type":"Bat","status":0},{"type":"IronShell","status":1}]},{},{},{},{},{},{"objectType":"ColorBall","subObjects":[{"type":"Bat","status":0},{"type":"IronShell","status":1}]},{"objectType":"ColorBall"},{"objectType":"ColorBomb","subObjects":[{"type":"Bat","status":0}]}],[{},{"objectType":"ColorBall"},{"objectType":"ColorBall","subObjects":[{"type":"Bat","status":0},{"type":"IronShell","status":1}]},{"objectType":"ColorBall"},{},{},{"objectType":"ColorBall"},{"objectType":"ColorBall","subObjects":[{"type":"Bat","status":0},{"type":"IronShell","status":1}]},{"objectType":"ColorBall"},{}],[{},{},{"objectType":"ColorBall"},{"objectType":"ColorBall"},{"objectType":"ColorBall"},{"objectType":"ColorBomb","subObjects":[{"type":"Bat","status":0}]},{"objectType":"ColorBall"},{"objectType":"ColorBall"},{"objectType":"ColorBall"},{},{}],[{},{"objectType":"ColorBall"},{"objectType":"ColorBall"},{},{"objectType":"EarthenPot"},{"objectType":"EarthenPot"},{},{"objectType":"ColorBall"},{"objectType":"ColorBall"},{}],[{},{},{"objectType":"ColorBall"},{"objectType":"ColorBall"},{"objectType":"ColorBall"},{"objectType":"EarthenPot"},{"objectType":"ColorBall"},{"objectType":"ColorBall"},{"objectType":"ColorBall"},{},{}],[{},{},{"objectType":"ColorBall"},{"objectType":"ColorBall"},{"objectType":"ColorBall"},{"objectType":"ColorBall"},{"objectType":"ColorBall"},{"objectType":"ColorBall"},{},{}],[{},{},{"objectType":"ColorBall"},{"objectType":"ColorBall","subObjects":[{"type":"Bat","status":0},{"type":"IronShell","status":0}]},{"objectType":"ColorBall","subObjects":[{"type":"Bat","status":0},{"type":"IronShell","status":0}]},{"objectType":"ColorBall","subObjects":[{"type":"Bat","status":0},{"type":"IronShell","status":0}]},{"objectType":"ColorBall","subObjects":[{"type":"Bat","status":0},{"type":"IronShell","status":0}]},{"objectType":"ColorBall","subObjects":[{"type":"Bat","status":0},{"type":"IronShell","status":0}]},{"objectType":"ColorBall"},{},{}],[{},{"objectType":"ColorBall"},{"objectType":"EarthenPot"},{"objectType":"EarthenPot"},{},{},{"objectType":"EarthenPot"},{"objectType":"EarthenPot"},{"objectType":"ColorBall"},{}],[{},{},{"objectType":"ColorBall"},{"objectType":"ColorBall","color":158691,"subObjects":[{"type":"Bat","status":0}]},{"objectType":"ColorBall","subObjects":[{"type":"Bat","status":0},{"type":"IronShell","status":1}]},{"objectType":"ColorBomb","subObjects":[{"type":"Bat","status":0}]},{"objectType":"ColorBall","color":16711935,"subObjects":[{"type":"Bat","status":0},{"type":"IronShell","status":1}]},{"objectType":"ColorBall","color":16711935,"subObjects":[{"type":"Bat","status":0}]},{"objectType":"ColorBall"},{},{}],[{},{"objectType":"ColorBall","color":834032},{"objectType":"ColorBall","color":16763392},{"objectType":"ColorBall","color":158691},{},{},{"objectType":"ColorBall","color":16711935},{"objectType":"ColorBall","color":16763392},{"objectType":"ColorBall","color":16530738},{}],[{"objectType":"ColorBomb","subObjects":[{"type":"Bat","status":0}]},{"objectType":"ColorBall"},{"objectType":"ColorBall","color":834032},{"objectType":"ColorBall","color":16763392},{"objectType":"ColorBall","color":158691},{"objectType":"EarthenPot"},{"objectType":"ColorBall","color":16711935},{"objectType":"ColorBall","color":16763392},{"objectType":"ColorBall","color":16530738},{"objectType":"ColorBall"},{"objectType":"ColorBomb","subObjects":[{"type":"Bat","status":0}]}],[{},{"objectType":"EarthenPot"},{"objectType":"ColorBall","color":834032},{"objectType":"ColorBall","color":16763392},{"objectType":"ColorBall","color":158691,"subObjects":[{"type":"Bat","status":0},{"type":"IronShell","status":1}]},{"objectType":"ColorBall","color":16711935,"subObjects":[{"type":"Bat","status":0},{"type":"IronShell","status":1}]},{"objectType":"ColorBall","color":16763392},{"objectType":"ColorBall","color":16530738},{"objectType":"EarthenPot"},{}],[{},{},{"objectType":"ColorBall","color":834032},{"objectType":"EarthenPot"},{},{},{},{"objectType":"EarthenPot"},{"objectType":"ColorBall","color":16530738},{},{}],[{},{},{"objectType":"ColorBall","color":834032},{"objectType":"ColorBall","color":16763392},{},{},{"objectType":"ColorBall","color":16763392},{"objectType":"ColorBall","color":16530738},{},{}]],"colorButtonOverlay":"green"}