{"isHard":false,"numberBullets":20,"bulletsColor":[],"bulletItems":{"BombBulletItem":0,"ElectricBulletBallItem":0,"RainbowBulletBallItem":0,"RocketBulletItem":0},"starsTarget":[9000,20000,31000],"missionType":"CollectBubbles","colors":[57396,9703300,15757844],"grid":[[{},{},{},{},{},{},{},{},{},{},{}],[{},{},{"objectType":"ColorBall"},{"objectType":"ColorBall"},{"objectType":"ColorBall"},{"objectType":"ColorBall"},{"objectType":"ColorBall"},{"objectType":"ColorBall"},{},{}],[{},{},{"objectType":"ColorBall"},{"objectType":"ColorBall"},{},{"objectType":"ColorBall","subObjects":[{"type":"HexagonWire","status":0}]},{},{"objectType":"ColorBall"},{"objectType":"ColorBall"},{},{}],[{},{"objectType":"ColorBall"},{},{"objectType":"ColorBall"},{},{},{"objectType":"ColorBall"},{},{"objectType":"ColorBall"},{}],[{},{"objectType":"ColorBall"},{"objectType":"ColorBall"},{"objectType":"ColorBall"},{"objectType":"ColorBall"},{},{"objectType":"ColorBall"},{"objectType":"ColorBall"},{"objectType":"ColorBall"},{"objectType":"ColorBall"},{}],[{"objectType":"ColorBall"},{},{"objectType":"RandomDirectionElectricBall","subObjects":[{"type":"HexagonWire","status":0}]},{},{"objectType":"ColorBall"},{"objectType":"ColorBall"},{},{"objectType":"ColorBall","subObjects":[{"type":"HexagonWire","status":0}]},{},{"objectType":"ColorBall"}],[{},{"objectType":"ColorBall"},{"objectType":"ColorBall"},{"objectType":"ColorBall"},{"objectType":"ColorBall"},{},{"objectType":"ColorBall"},{"objectType":"ColorBall"},{"objectType":"ColorBall"},{"objectType":"ColorBall"},{}],[{},{"objectType":"ColorBall"},{},{"objectType":"ColorBall"},{},{},{"objectType":"ColorBall"},{},{"objectType":"ColorBall"},{}],[{},{},{"objectType":"ColorBall"},{"objectType":"ColorBall"},{},{},{},{"objectType":"ColorBall"},{"objectType":"ColorBall"},{},{}],[{},{},{"objectType":"ColorBall"},{},{"objectType":"RandomDirectionElectricBall","status":1},{"objectType":"RandomDirectionElectricBall","status":2},{},{"objectType":"ColorBall"},{},{}],[{},{"objectType":"ColorBall"},{"objectType":"ColorBall"},{"objectType":"ColorBall"},{"objectType":"ColorBall"},{"objectType":"ColorBall"},{"objectType":"ColorBall"},{"objectType":"ColorBall"},{"objectType":"ColorBall"},{"objectType":"ColorBall"},{}],[{},{},{"objectType":"ColorBall"},{},{"objectType":"ColorBall"},{"objectType":"ColorBall"},{},{"objectType":"ColorBall"},{},{}],[{},{},{"objectType":"ColorBall"},{"objectType":"ColorBall"},{},{},{},{"objectType":"ColorBall"},{"objectType":"ColorBall"},{},{}],[{},{"objectType":"ColorBall"},{},{"objectType":"ColorBall"},{},{},{"objectType":"ColorBall"},{},{"objectType":"ColorBall"},{}],[{},{"objectType":"ColorBall"},{"objectType":"ColorBall"},{"objectType":"ColorBall"},{"objectType":"ColorBall"},{},{"objectType":"ColorBall"},{"objectType":"ColorBall"},{"objectType":"ColorBall"},{"objectType":"ColorBall"},{}],[{"objectType":"ColorBall"},{},{"objectType":"ColorBall","subObjects":[{"type":"HexagonWire","status":0}]},{},{"objectType":"ColorBall"},{"objectType":"ColorBall"},{},{"objectType":"RandomDirectionElectricBall","subObjects":[{"type":"HexagonWire","status":0}]},{},{"objectType":"ColorBall"}],[{},{"objectType":"ColorBall"},{"objectType":"ColorBall"},{"objectType":"ColorBall"},{"objectType":"ColorBall"},{},{"objectType":"ColorBall"},{"objectType":"ColorBall"},{"objectType":"ColorBall"},{"objectType":"ColorBall"},{}],[{},{"objectType":"ColorBall"},{},{"objectType":"ColorBall"},{},{},{"objectType":"ColorBall"},{},{"objectType":"ColorBall"},{}],[{},{},{"objectType":"ColorBall"},{"objectType":"ColorBall"},{},{},{},{"objectType":"ColorBall"},{"objectType":"ColorBall"},{},{}],[{},{},{"objectType":"ColorBall"},{},{"objectType":"RandomDirectionElectricBall","status":1},{"objectType":"RandomDirectionElectricBall","status":2},{},{"objectType":"ColorBall"},{},{}],[{},{"objectType":"ColorBall"},{"objectType":"ColorBall"},{"objectType":"ColorBall"},{"objectType":"ColorBall"},{"objectType":"ColorBall"},{"objectType":"ColorBall"},{"objectType":"ColorBall"},{"objectType":"ColorBall"},{"objectType":"ColorBall"},{}],[{},{},{},{},{"objectType":"ColorBall"},{"objectType":"ColorBall"},{},{},{},{}],[{},{"objectType":"ColorBall"},{},{},{},{"objectType":"ColorBall"},{},{},{},{"objectType":"ColorBall"},{}],[{},{"objectType":"ColorBall"},{},{},{"objectType":"ColorBall"},{"objectType":"ColorBall"},{},{},{"objectType":"ColorBall"},{}],[{},{"objectType":"ColorBall"},{},{},{"objectType":"ColorBall"},{},{"objectType":"ColorBall"},{},{},{"objectType":"ColorBall"},{}],[{"objectType":"ColorBall"},{},{},{"objectType":"ColorBall"},{},{},{"objectType":"ColorBall"},{},{},{"objectType":"ColorBall"}],[{"objectType":"RandomDirectionElectricBall","status":1,"subObjects":[{"type":"HexagonWire","status":0}]},{"objectType":"ColorBall"},{},{"objectType":"ColorBall"},{},{},{},{"objectType":"ColorBall"},{},{"objectType":"ColorBall"},{"objectType":"RandomDirectionElectricBall","status":2,"subObjects":[{"type":"HexagonWire","status":0}]}],[{"objectType":"ColorBall"},{},{},{"objectType":"ColorBall"},{},{},{"objectType":"ColorBall"},{},{},{"objectType":"ColorBall"}],[{},{"objectType":"ColorBall"},{},{},{"objectType":"ColorBall"},{},{"objectType":"ColorBall"},{},{},{"objectType":"ColorBall"},{}],[{},{"objectType":"ColorBall"},{},{},{"objectType":"ColorBall"},{"objectType":"ColorBall"},{},{},{"objectType":"ColorBall"},{}],[{},{"objectType":"ColorBall"},{},{},{},{"objectType":"RandomDirectionElectricBall","status":1},{},{},{},{"objectType":"ColorBall"},{}],[{},{},{},{},{"objectType":"ColorBall"},{"objectType":"ColorBall"},{},{},{},{}],[{},{"objectType":"ColorBall"},{},{},{"objectType":"ColorBall"},{},{"objectType":"ColorBall"},{},{},{"objectType":"ColorBall"},{}],[{},{"objectType":"ColorBall"},{},{"objectType":"ColorBall"},{},{},{"objectType":"ColorBall"},{},{"objectType":"ColorBall"},{}],[{},{"objectType":"ColorBall"},{},{"objectType":"ColorBall"},{},{},{},{"objectType":"ColorBall"},{},{"objectType":"ColorBall"},{}],[{"objectType":"RandomDirectionElectricBall","subObjects":[{"type":"HexagonWire","status":0}]},{},{},{"objectType":"ColorBall","color":57396},{},{},{"objectType":"ColorBall","color":9703300},{},{},{"objectType":"RandomDirectionElectricBall","status":3,"subObjects":[{"type":"HexagonWire","status":0}]}],[{},{"objectType":"ColorBall","color":15757844},{},{},{"objectType":"ColorBall","color":57396},{},{"objectType":"ColorBall","color":9703300},{},{},{"objectType":"ColorBall","color":15757844},{}],[{},{"objectType":"ColorBall","color":15757844},{},{},{"objectType":"ColorBall","color":57396},{"objectType":"ColorBall","color":9703300},{},{},{"objectType":"ColorBall","color":15757844},{}],[{},{"objectType":"ColorBall","color":15757844},{},{},{},{"objectType":"RandomDirectionElectricBall","status":2},{},{},{},{"objectType":"ColorBall","color":15757844},{}]],"colorButtonOverlay":"green"}