{"isHard":false,"numberBullets":25,"bulletsColor":[16711935,16763392],"bulletItems":{"BombBulletItem":0,"ElectricBulletBallItem":0,"RainbowBulletBallItem":0,"RocketBulletItem":0},"starsTarget":[7000,12000,20000],"missionType":"CollectBubbles","colors":[16763392,16711935,158691],"grid":[[{},{"objectType":"ColorBall","color":16763392},{"objectType":"ColorBall","color":16763392},{"objectType":"ThunderBall","color":16763392},{"objectType":"ColorBall","color":16711935},{"objectType":"ColorBall","color":16711935},{"objectType":"ColorBall","color":16711935},{"objectType":"ColorBall","color":158691},{"objectType":"ColorBall","color":158691},{"objectType":"ColorBall","color":158691},{}],[{"objectType":"ColorBall"},{"objectType":"ColorBall"},{"objectType":"ColorBall"},{"objectType":"ColorBall","color":16763392},{"objectType":"ColorBall","color":16711935},{"objectType":"ColorBall","color":16711935},{"objectType":"ColorBall","color":158691},{"objectType":"ColorBall"},{"objectType":"ColorBall"},{"objectType":"ColorBall"}],[{},{"objectType":"ThunderBall","subObjects":[{"type":"HexagonWire","status":0}]},{"objectType":"WhiteBall"},{"objectType":"WhiteBall"},{"objectType":"ColorBall","color":16763392},{},{"objectType":"ColorBall","color":158691},{"objectType":"WhiteBall"},{"objectType":"WhiteBall"},{"objectType":"ThunderBall","subObjects":[{"type":"HexagonWire","status":0}]},{}],[{"objectType":"ColorBall"},{},{},{"objectType":"WhiteBall"},{"objectType":"WhiteBall"},{"objectType":"WhiteBall"},{"objectType":"WhiteBall"},{},{},{"objectType":"ColorBall"}],[{},{"objectType":"ColorBall"},{"objectType":"WhiteBall"},{},{"objectType":"WhiteBall"},{"objectType":"WhiteBall","subObjects":[{"type":"HexagonWire","status":0}]},{"objectType":"WhiteBall"},{},{"objectType":"WhiteBall"},{"objectType":"ColorBall"},{}],[{"objectType":"ColorBall"},{"objectType":"ColorBall"},{"objectType":"WhiteBall"},{"objectType":"WhiteBall"},{"objectType":"WhiteBall"},{"objectType":"WhiteBall"},{"objectType":"WhiteBall"},{"objectType":"WhiteBall"},{"objectType":"ThunderBall"},{"objectType":"ColorBall"}],[{},{"objectType":"ColorBall"},{"objectType":"ColorBall"},{},{},{"objectType":"RandomDirectionElectricBall","status":1},{},{},{"objectType":"ColorBall"},{"objectType":"ColorBall"},{}],[{},{},{},{},{},{},{},{},{},{}],[{},{"objectType":"ColorBall","color":16763392},{"objectType":"ColorBall","color":16711935},{"objectType":"ColorBall"},{"objectType":"ColorBall"},{"objectType":"ThunderBall"},{"objectType":"ColorBall"},{"objectType":"ColorBall"},{"objectType":"ColorBall","color":16711935},{"objectType":"ColorBall","color":158691},{}],[{"objectType":"ColorBall","color":16763392},{"objectType":"ThunderBall","subObjects":[{"type":"HexagonWire","status":0}]},{"objectType":"ColorBall","color":16711935},{"objectType":"ColorBall"},{"objectType":"ColorBall"},{"objectType":"ColorBall"},{"objectType":"ColorBall"},{"objectType":"ColorBall","color":16711935},{"objectType":"ThunderBall","subObjects":[{"type":"HexagonWire","status":0}]},{"objectType":"ColorBall","color":158691}],[{},{"objectType":"ColorBall","color":16763392},{"objectType":"ColorBall","color":16711935},{"objectType":"WhiteBall"},{"objectType":"ColorBall"},{"objectType":"WhiteBall"},{"objectType":"ColorBall"},{"objectType":"WhiteBall"},{"objectType":"ColorBall","color":16711935},{"objectType":"ColorBall","color":158691},{}],[{},{"objectType":"ColorBall","color":158691},{},{"objectType":"WhiteBall"},{"objectType":"WhiteBall"},{"objectType":"WhiteBall"},{"objectType":"WhiteBall"},{},{"objectType":"ColorBall","color":16763392},{}],[{},{},{"objectType":"ColorBall","color":16763392},{},{"objectType":"RandomDirectionElectricBall","status":1},{"objectType":"WhiteBall","subObjects":[{"type":"HexagonWire","status":0}]},{"objectType":"RandomDirectionElectricBall","status":1},{},{"objectType":"ColorBall","color":16711935},{},{}],[{},{},{"objectType":"ColorBall","color":16711935},{},{},{},{},{"objectType":"ColorBall","color":16763392},{},{}],[{},{},{},{"objectType":"ColorBall","color":158691},{},{},{},{"objectType":"ColorBall","color":16711935},{},{},{}],[{},{},{},{"objectType":"ColorBall","color":16763392},{},{},{"objectType":"ColorBall","color":158691},{},{},{}],[{},{},{},{},{"objectType":"ColorBall","color":158691},{"objectType":"ThunderBall","color":158691},{"objectType":"ColorBall","color":158691},{},{},{},{}],[{},{},{},{},{},{},{},{},{},{}],[{},{},{},{},{},{},{},{},{},{},{}],[{},{},{"objectType":"ColorBall","color":16763392},{"objectType":"ColorBall","color":16763392},{"objectType":"ColorBall","color":16763392},{"objectType":"ColorBall","color":16763392},{"objectType":"ColorBall","color":16763392},{"objectType":"ColorBall","color":16763392},{},{}],[{},{},{"objectType":"ColorBall","color":16763392},{"objectType":"ColorBall","color":158691},{"objectType":"ColorBall","color":158691},{"objectType":"ColorBall","color":158691},{"objectType":"ColorBall","color":158691},{"objectType":"ThunderBall","color":158691},{"objectType":"ColorBall","color":16763392},{},{}],[{},{"objectType":"ColorBall","color":16763392},{"objectType":"ColorBall","color":158691},{"objectType":"ColorBall","color":16711935},{"objectType":"ColorBall","color":16711935},{"objectType":"ColorBall","color":16711935},{"objectType":"ColorBall","color":16711935},{"objectType":"ColorBall","color":158691},{"objectType":"ColorBall","color":16763392},{}],[{},{"objectType":"ColorBall","color":16763392},{"objectType":"ColorBall","color":16711935},{"objectType":"ColorBall","color":16711935},{"objectType":"WhiteBall"},{"objectType":"ColorBall","color":16711935},{"objectType":"WhiteBall"},{"objectType":"ColorBall","color":16711935},{"objectType":"ColorBall","color":16711935},{"objectType":"ColorBall","color":16763392},{}],[{"objectType":"ColorBall","color":16763392},{"objectType":"ColorBall","color":16711935},{"objectType":"WhiteBall"},{"objectType":"WhiteBall","subObjects":[{"type":"HexagonWire","status":0}]},{"objectType":"RandomDirectionElectricBall"},{"objectType":"RandomDirectionElectricBall","status":3},{"objectType":"WhiteBall","subObjects":[{"type":"HexagonWire","status":0}]},{"objectType":"WhiteBall"},{"objectType":"ColorBall","color":16711935},{"objectType":"ColorBall","color":16763392}],[{},{"objectType":"ColorBall","color":16763392},{"objectType":"ColorBall","color":16763392},{"objectType":"ColorBall","color":16711935},{"objectType":"ColorBall","color":16763392},{"objectType":"WhiteBall","subObjects":[{"type":"HexagonWire","status":0}]},{"objectType":"ColorBall","color":16763392},{"objectType":"ColorBall","color":16711935},{"objectType":"ColorBall","color":16763392},{"objectType":"ColorBall","color":16763392},{}],[{},{"objectType":"ColorBall","color":16711935},{"objectType":"ColorBall","color":158691},{"objectType":"ThunderBall","color":16711935},{"objectType":"WhiteBall"},{"objectType":"WhiteBall"},{"objectType":"ColorBall","color":16711935},{"objectType":"ColorBall","color":158691},{"objectType":"ColorBall","color":16711935},{}],[{},{},{"objectType":"ColorBall","color":16711935},{"objectType":"ColorBall","color":158691},{"objectType":"ColorBall","color":16763392},{"objectType":"ColorBall","color":16763392},{"objectType":"ColorBall","color":16763392},{"objectType":"ColorBall","color":158691},{"objectType":"ColorBall","color":16711935},{},{}],[{},{},{"objectType":"ColorBall","color":16711935},{"objectType":"ColorBall","color":16711935},{"objectType":"ColorBall","color":16711935},{"objectType":"ColorBall","color":16711935},{"objectType":"ColorBall","color":16711935},{"objectType":"ColorBall","color":16711935},{},{}]],"colorButtonOverlay":"purple"}