{"isHard":false,"numberBullets":26,"bulletsColor":[16530738,9703300],"bulletItems":{"BombBulletItem":0,"ElectricBulletBallItem":0,"RainbowBulletBallItem":0,"RocketBulletItem":0},"starsTarget":[6500,1000,19500],"missionType":"CollectGems","colors":[158691,16530738,9703300,834032,16763392],"grid":[[{},{},{"objectType":"WhiteBall"},{"objectType":"WhiteBall"},{"objectType":"WhiteBall"},{"objectType":"WhiteBall"},{"objectType":"WhiteBall"},{"objectType":"WhiteBall"},{"objectType":"WhiteBall"},{"objectType":"WhiteBall"},{"objectType":"WhiteBall"},{},{}],[{},{},{"objectType":"ColorBall","color":158691},{"objectType":"ColorBall","color":158691},{},{"objectType":"ColorBall","color":16530738},{"objectType":"ColorBall","color":16530738},{},{"objectType":"ColorBall","color":158691},{"objectType":"ColorBall","color":158691},{},{}],[{},{},{"objectType":"ColorBall","color":9703300},{"objectType":"GemBall"},{"objectType":"ColorBall","color":158691},{"objectType":"ColorBall","color":16530738},{"objectType":"GemBall","subObjects":[{"type":"Spider","status":0}]},{"objectType":"ColorBall","color":16530738},{"objectType":"ColorBall","color":834032},{"objectType":"GemBall"},{"objectType":"ColorBall","color":834032},{},{}],[{},{},{"objectType":"ColorBall","color":158691},{"objectType":"ColorBall","color":158691},{},{"objectType":"ColorBall","color":158691},{"objectType":"ColorBall","color":158691},{},{"objectType":"ColorBall","color":834032},{"objectType":"ColorBall","color":834032},{},{}],[{},{"objectType":"ColorBall","color":834032},{"objectType":"ColorBall","color":834032},{"objectType":"WhiteBall"},{"objectType":"ColorBall","color":16763392},{"objectType":"ColorBall","color":16763392},{"objectType":"WhiteBall"},{"objectType":"ColorBall","color":9703300},{"objectType":"ColorBall","color":9703300},{"objectType":"WhiteBall"},{"objectType":"ColorBall","color":834032},{"objectType":"ColorBall","color":16530738},{}],[{"objectType":"ColorBall","color":834032},{"objectType":"GemBall","subObjects":[{"type":"Spider","status":0}]},{"objectType":"ColorBall","color":834032},{"objectType":"ColorBall","color":834032},{"objectType":"GemBall"},{"objectType":"ColorBall","color":16530738},{"objectType":"ColorBall","color":16530738},{"objectType":"GemBall"},{"objectType":"ColorBall","color":9703300},{"objectType":"ColorBall","color":834032},{"objectType":"GemBall","subObjects":[{"type":"Spider","status":0}]},{"objectType":"ColorBall","color":16530738}],[{},{"objectType":"ColorBall","color":834032},{"objectType":"ColorBall","color":834032},{"objectType":"WhiteBall"},{"objectType":"ColorBall","color":16763392},{"objectType":"ColorBall","color":16530738},{"objectType":"WhiteBall"},{"objectType":"ColorBall","color":16530738},{"objectType":"ColorBall","color":9703300},{"objectType":"WhiteBall"},{"objectType":"ColorBall","color":834032},{"objectType":"ColorBall","color":16530738},{}],[{},{},{"objectType":"ColorBall","color":834032},{"objectType":"ColorBall","color":16763392},{},{"objectType":"ColorBall","color":16530738},{"objectType":"ColorBall","color":16530738},{},{"objectType":"ColorBall"},{"objectType":"ColorBall","color":16763392},{},{}],[{},{},{"objectType":"ColorBall","color":9703300},{"objectType":"GemBall"},{"objectType":"ColorBall","color":16763392},{"objectType":"ColorBall","color":158691},{"objectType":"GemBall","subObjects":[{"type":"Spider","status":0}]},{"objectType":"ColorBall","color":158691},{"objectType":"ColorBall","color":834032},{"objectType":"GemBall"},{"objectType":"ColorBall","color":16763392},{},{}],[{},{},{"objectType":"ColorBall","color":9703300},{"objectType":"ColorBall","color":16763392},{},{"objectType":"ColorBall","color":158691},{"objectType":"ColorBall","color":158691},{},{"objectType":"ColorBall","color":16763392},{"objectType":"ColorBall","color":16763392},{},{}],[{},{"objectType":"ColorBall","color":9703300},{"objectType":"ColorBall","color":16763392},{"objectType":"WhiteBall"},{"objectType":"ColorBall","color":158691},{"objectType":"ColorBall","color":158691},{"objectType":"WhiteBall"},{"objectType":"ColorBall","color":16763392},{"objectType":"ColorBall","color":16763392},{"objectType":"WhiteBall"},{"objectType":"ColorBall","color":158691},{"objectType":"ColorBall","color":158691},{}],[{"objectType":"ColorBall","color":9703300},{"objectType":"GemBall"},{"objectType":"ColorBall","color":16763392},{"objectType":"ColorBall","color":158691},{"objectType":"GemBall"},{"objectType":"ColorBall","color":834032},{"objectType":"ColorBall","color":834032},{"objectType":"GemBall"},{"objectType":"ColorBall","color":834032},{"objectType":"ColorBall","color":158691},{"objectType":"GemBall"},{"objectType":"ColorBall","color":158691}],[{},{"objectType":"ColorBall","color":9703300},{"objectType":"ColorBall","color":16763392},{"objectType":"WhiteBall"},{"objectType":"ColorBall","color":158691},{"objectType":"ColorBall","color":158691},{"objectType":"WhiteBall"},{"objectType":"ColorBall","color":834032},{"objectType":"ColorBall","color":834032},{"objectType":"WhiteBall"},{"objectType":"ColorBall","color":9703300},{"objectType":"ColorBall","color":158691},{}],[{},{},{"objectType":"ColorBall","color":9703300},{"objectType":"ColorBall","color":9703300},{},{"objectType":"ColorBall","color":16530738},{"objectType":"ColorBall","color":16763392},{},{"objectType":"ColorBall","color":9703300},{"objectType":"ColorBall","color":9703300},{},{}],[{},{},{"objectType":"ColorBall","color":9703300},{"objectType":"GemBall"},{"objectType":"ColorBall","color":16530738},{"objectType":"ColorBall","color":16530738},{"objectType":"GemBall","subObjects":[{"type":"Spider","status":0}]},{"objectType":"ColorBall","color":9703300},{"objectType":"ColorBall","color":16530738},{"objectType":"GemBall"},{"objectType":"ColorBall","color":16530738},{},{}],[{},{},{"objectType":"ColorBall","color":9703300},{"objectType":"ColorBall","color":9703300},{},{"objectType":"ColorBall","color":16530738},{"objectType":"ColorBall","color":9703300},{},{"objectType":"ColorBall","color":16530738},{"objectType":"ColorBall","color":16530738},{},{}],[{},{},{"objectType":"WhiteBall"},{"objectType":"WhiteBall"},{"objectType":"WhiteBall"},{"objectType":"WhiteBall"},{"objectType":"WhiteBall"},{"objectType":"WhiteBall"},{"objectType":"WhiteBall"},{"objectType":"WhiteBall"},{"objectType":"WhiteBall"},{},{}]],"colorButtonOverlay":"pink"}