{"isHard":false,"numberBullets":40,"bulletsColor":[],"bulletItems":{"BombBulletItem":0,"ElectricBulletBallItem":0,"RainbowBulletBallItem":0,"RocketBulletItem":0},"starsTarget":[11000,30000,51000],"missionType":"CollectBubbles","colors":[158691,57396,16530738,16763392],"grid":[[{},{},{"objectType":"TwoColorsBall","subObjects":[{"type":"SpiderWeb","status":0}]},{"objectType":"ColorBall"},{"objectType":"TwoColorsBall","subObjects":[{"type":"SpiderWeb","status":0}]},{"objectType":"ColorBall"},{},{"objectType":"ColorBall"},{"objectType":"TwoColorsBall","subObjects":[{"type":"SpiderWeb","status":0}]},{"objectType":"ColorBall"},{"objectType":"TwoColorsBall","subObjects":[{"type":"SpiderWeb","status":0}]},{},{}],[{},{"objectType":"ColorBall"},{"objectType":"TwoColorsBall","subObjects":[{"type":"SpiderWeb","status":0}]},{"objectType":"ColorBall"},{"objectType":"TwoColorsBall","subObjects":[{"type":"SpiderWeb","status":0}]},{"objectType":"ColorBall"},{"objectType":"ColorBall"},{"objectType":"TwoColorsBall","subObjects":[{"type":"SpiderWeb","status":0}]},{"objectType":"ColorBall"},{"objectType":"TwoColorsBall","subObjects":[{"type":"SpiderWeb","status":0}]},{"objectType":"ColorBall"},{}],[{},{"objectType":"TwoColorsBall","subObjects":[{"type":"SpiderWeb","status":0}]},{"objectType":"ColorBall"},{"objectType":"TwoColorsBall","subObjects":[{"type":"SpiderWeb","status":0}]},{"objectType":"TwoColorsBall"},{"objectType":"TwoColorsBall","subObjects":[{"type":"SpiderWeb","status":0}]},{"objectType":"ColorBomb"},{"objectType":"TwoColorsBall","subObjects":[{"type":"SpiderWeb","status":0}]},{"objectType":"ColorBall"},{"objectType":"TwoColorsBall","subObjects":[{"type":"SpiderWeb","status":0}]},{"objectType":"ColorBall"},{"objectType":"TwoColorsBall","subObjects":[{"type":"SpiderWeb","status":0}]},{}],[{"objectType":"ColorBall"},{"objectType":"TwoColorsBall","subObjects":[{"type":"SpiderWeb","status":0}]},{"objectType":"ColorBall"},{"objectType":"TwoColorsBall","subObjects":[{"type":"SpiderWeb","status":0}]},{},{"objectType":"TwoColorsBall","subObjects":[{"type":"SpiderWeb","status":0}]},{"objectType":"TwoColorsBall","subObjects":[{"type":"SpiderWeb","status":0}]},{},{"objectType":"TwoColorsBall","subObjects":[{"type":"SpiderWeb","status":0}]},{"objectType":"ColorBall"},{"objectType":"TwoColorsBall","subObjects":[{"type":"SpiderWeb","status":0}]},{"objectType":"ColorBall"}],[{},{"objectType":"ColorBall"},{"objectType":"TwoColorsBall","subObjects":[{"type":"SpiderWeb","status":0}]},{"objectType":"ColorBall"},{"objectType":"TwoColorsBall","subObjects":[{"type":"SpiderWeb","status":0}]},{},{},{},{"objectType":"TwoColorsBall","subObjects":[{"type":"SpiderWeb","status":0}]},{"objectType":"ColorBall"},{"objectType":"TwoColorsBall","subObjects":[{"type":"SpiderWeb","status":0}]},{"objectType":"ColorBall"},{}],[{"objectType":"ColorBall"},{"objectType":"ColorBall"},{"objectType":"TwoColorsBall","subObjects":[{"type":"SpiderWeb","status":0}]},{"objectType":"ColorBall"},{},{"objectType":"ColorBall"},{"objectType":"ColorBall"},{},{"objectType":"ColorBall"},{"objectType":"TwoColorsBall","subObjects":[{"type":"SpiderWeb","status":0}]},{"objectType":"ColorBall"},{"objectType":"ColorBall"}],[{},{"objectType":"ColorBall"},{"objectType":"ColorBall"},{"objectType":"TwoColorsBall","subObjects":[{"type":"SpiderWeb","status":0}]},{"objectType":"ColorBall"},{"objectType":"ColorBall"},{"objectType":"ColorBomb"},{"objectType":"ColorBall"},{"objectType":"ColorBall"},{"objectType":"TwoColorsBall","subObjects":[{"type":"SpiderWeb","status":0}]},{"objectType":"ColorBall"},{"objectType":"ColorBall"},{}],[{},{"objectType":"ColorBall"},{"objectType":"ColorBall"},{"objectType":"TwoColorsBall","subObjects":[{"type":"SpiderWeb","status":0}]},{"objectType":"ColorBall"},{"objectType":"ColorBall"},{"objectType":"ColorBall"},{"objectType":"ColorBall"},{"objectType":"TwoColorsBall","subObjects":[{"type":"SpiderWeb","status":0}]},{"objectType":"ColorBall"},{"objectType":"ColorBall"},{}],[{},{},{"objectType":"ColorBall"},{"objectType":"ColorBall"},{"objectType":"TwoColorsBall","subObjects":[{"type":"SpiderWeb","status":0}]},{"objectType":"ColorBall"},{},{"objectType":"ColorBall"},{"objectType":"TwoColorsBall","subObjects":[{"type":"SpiderWeb","status":0}]},{"objectType":"ColorBall"},{"objectType":"ColorBall"},{},{}],[{},{"objectType":"ThunderBall"},{"objectType":"ColorBall"},{},{"objectType":"ThunderBall"},{"objectType":"ColorBall"},{"objectType":"ColorBall"},{"objectType":"ThunderBall"},{},{"objectType":"ColorBall"},{"objectType":"ThunderBall"},{}],[{},{"objectType":"ColorBall"},{"objectType":"ColorBall"},{},{},{"objectType":"ColorBall"},{},{"objectType":"ColorBall"},{},{},{"objectType":"ColorBall"},{"objectType":"ColorBall"},{}],[{},{"objectType":"ColorBall"},{"objectType":"ColorBall"},{},{},{"objectType":"TwoColorsBall","subObjects":[{"type":"SpiderWeb","status":0}]},{"objectType":"TwoColorsBall","subObjects":[{"type":"SpiderWeb","status":0}]},{},{},{"objectType":"ColorBall"},{"objectType":"ColorBall"},{}],[{},{},{"objectType":"ColorBall"},{"objectType":"TwoColorsBall","subObjects":[{"type":"SpiderWeb","status":0}]},{"objectType":"TwoColorsBall","subObjects":[{"type":"SpiderWeb","status":0}]},{"objectType":"TwoColorsBall","subObjects":[{"type":"SpiderWeb","status":0}]},{"objectType":"ColorBomb","subObjects":[{"type":"SpiderWeb","status":0}]},{"objectType":"TwoColorsBall","subObjects":[{"type":"SpiderWeb","status":0}]},{"objectType":"TwoColorsBall","subObjects":[{"type":"SpiderWeb","status":0}]},{"objectType":"TwoColorsBall","subObjects":[{"type":"SpiderWeb","status":0}]},{"objectType":"ColorBall"},{},{}],[{},{"objectType":"ColorBall"},{"objectType":"ColorBall"},{},{},{"objectType":"TwoColorsBall","subObjects":[{"type":"SpiderWeb","status":0}]},{"objectType":"TwoColorsBall","subObjects":[{"type":"SpiderWeb","status":0}]},{},{},{"objectType":"ColorBall"},{"objectType":"ColorBall"},{}],[{},{"objectType":"ColorBall"},{"objectType":"ColorBall"},{},{},{"objectType":"ColorBall"},{},{"objectType":"ColorBall"},{},{},{"objectType":"ColorBall"},{"objectType":"ColorBall"},{}],[{},{"objectType":"ThunderBall"},{"objectType":"ColorBall"},{},{"objectType":"ThunderBall"},{"objectType":"ColorBall"},{"objectType":"ColorBall"},{"objectType":"ThunderBall"},{},{"objectType":"ColorBall"},{"objectType":"ThunderBall"},{}],[{},{},{"objectType":"ColorBall"},{},{},{},{},{},{},{},{"objectType":"ColorBall"},{},{}],[{},{"objectType":"TwoColorsBall","subObjects":[{"type":"SpiderWeb","status":0}]},{"objectType":"TwoColorsBall","subObjects":[{"type":"SpiderWeb","status":0}]},{"objectType":"ColorBall"},{"objectType":"ColorBall"},{"objectType":"ColorBall"},{"objectType":"ColorBall"},{"objectType":"ColorBall"},{"objectType":"ColorBall"},{"objectType":"TwoColorsBall","subObjects":[{"type":"SpiderWeb","status":0}]},{"objectType":"TwoColorsBall","subObjects":[{"type":"SpiderWeb","status":0}]},{}],[{},{"objectType":"TwoColorsBall","subObjects":[{"type":"SpiderWeb","status":0}]},{"objectType":"ColorBomb"},{"objectType":"TwoColorsBall","subObjects":[{"type":"SpiderWeb","status":0}]},{"objectType":"ThunderBall"},{"objectType":"ColorBall"},{"objectType":"ColorBall"},{"objectType":"ColorBall"},{"objectType":"ColorBall"},{"objectType":"TwoColorsBall","subObjects":[{"type":"SpiderWeb","status":0}]},{"objectType":"ColorBomb"},{"objectType":"TwoColorsBall","subObjects":[{"type":"SpiderWeb","status":0}]},{}],[{},{"objectType":"TwoColorsBall","subObjects":[{"type":"SpiderWeb","status":0}]},{"objectType":"TwoColorsBall","subObjects":[{"type":"SpiderWeb","status":0}]},{},{},{"objectType":"ColorBall"},{"objectType":"ColorBall"},{},{},{"objectType":"TwoColorsBall","subObjects":[{"type":"SpiderWeb","status":0}]},{"objectType":"TwoColorsBall","subObjects":[{"type":"SpiderWeb","status":0}]},{}],[{},{"objectType":"TwoColorsBall","subObjects":[{"type":"SpiderWeb","status":0}]},{"objectType":"ColorBall"},{"objectType":"TwoColorsBall","subObjects":[{"type":"SpiderWeb","status":0}]},{},{},{"objectType":"ThunderBall"},{},{},{"objectType":"TwoColorsBall","subObjects":[{"type":"SpiderWeb","status":0}]},{"objectType":"ColorBall"},{"objectType":"TwoColorsBall","subObjects":[{"type":"SpiderWeb","status":0}]},{}],[{},{"objectType":"TwoColorsBall","subObjects":[{"type":"SpiderWeb","status":0}]},{"objectType":"TwoColorsBall","subObjects":[{"type":"SpiderWeb","status":0}]},{"objectType":"ColorBall"},{"objectType":"ColorBall"},{"objectType":"ColorBall"},{"objectType":"ColorBall"},{"objectType":"ColorBall"},{"objectType":"ThunderBall"},{"objectType":"TwoColorsBall","subObjects":[{"type":"SpiderWeb","status":0}]},{"objectType":"TwoColorsBall","subObjects":[{"type":"SpiderWeb","status":0}]},{}],[{},{"objectType":"TwoColorsBall","subObjects":[{"type":"SpiderWeb","status":0}]},{"objectType":"ColorBall"},{"objectType":"TwoColorsBall","subObjects":[{"type":"SpiderWeb","status":0}]},{"objectType":"ColorBall"},{"objectType":"ColorBall"},{"objectType":"ColorBomb"},{"objectType":"ColorBall"},{"objectType":"ColorBall"},{"objectType":"TwoColorsBall","subObjects":[{"type":"SpiderWeb","status":0}]},{"objectType":"ColorBall"},{"objectType":"TwoColorsBall","subObjects":[{"type":"SpiderWeb","status":0}]},{}],[{},{"objectType":"TwoColorsBall","subObjects":[{"type":"SpiderWeb","status":0}]},{"objectType":"TwoColorsBall","subObjects":[{"type":"SpiderWeb","status":0}]},{},{},{"objectType":"ColorBall"},{"objectType":"ColorBall"},{},{},{"objectType":"TwoColorsBall","subObjects":[{"type":"SpiderWeb","status":0}]},{"objectType":"TwoColorsBall","subObjects":[{"type":"SpiderWeb","status":0}]},{}],[{},{},{"objectType":"TwoColorsBall","subObjects":[{"type":"SpiderWeb","status":0}]},{"objectType":"TwoColorsBall","subObjects":[{"type":"SpiderWeb","status":0}]},{},{},{"objectType":"ThunderBall"},{},{},{"objectType":"TwoColorsBall","subObjects":[{"type":"SpiderWeb","status":0}]},{"objectType":"TwoColorsBall","subObjects":[{"type":"SpiderWeb","status":0}]},{},{}],[{},{},{"objectType":"TwoColorsBall","subObjects":[{"type":"SpiderWeb","status":0}]},{"objectType":"TwoColorsBall","subObjects":[{"type":"SpiderWeb","status":0}]},{"objectType":"ColorBall"},{"objectType":"ColorBall"},{"objectType":"ColorBall"},{"objectType":"ColorBall"},{"objectType":"TwoColorsBall","subObjects":[{"type":"SpiderWeb","status":0}]},{"objectType":"TwoColorsBall","subObjects":[{"type":"SpiderWeb","status":0}]},{},{}],[{},{},{},{"objectType":"TwoColorsBall","subObjects":[{"type":"SpiderWeb","status":0}]},{"objectType":"TwoColorsBall","subObjects":[{"type":"SpiderWeb","status":0}]},{"objectType":"ThunderBall"},{"objectType":"ColorBall"},{"objectType":"ColorBall"},{"objectType":"TwoColorsBall","subObjects":[{"type":"SpiderWeb","status":0}]},{"objectType":"TwoColorsBall","subObjects":[{"type":"SpiderWeb","status":0}]},{},{},{}],[{},{},{"objectType":"TwoColorsBall","subObjects":[{"type":"SpiderWeb","status":0}]},{"objectType":"TwoColorsBall","subObjects":[{"type":"SpiderWeb","status":0}]},{},{"objectType":"ColorBall"},{"objectType":"ColorBall"},{},{"objectType":"TwoColorsBall","subObjects":[{"type":"SpiderWeb","status":0}]},{"objectType":"TwoColorsBall","subObjects":[{"type":"SpiderWeb","status":0}]},{},{}],[{},{},{"objectType":"TwoColorsBall","subObjects":[{"type":"SpiderWeb","status":0}]},{"objectType":"TwoColorsBall","subObjects":[{"type":"SpiderWeb","status":0}]},{},{},{"objectType":"ThunderBall"},{},{},{"objectType":"TwoColorsBall","subObjects":[{"type":"SpiderWeb","status":0}]},{"objectType":"TwoColorsBall","subObjects":[{"type":"SpiderWeb","status":0}]},{},{}],[{},{},{"objectType":"TwoColorsBall","subObjects":[{"type":"SpiderWeb","status":0}]},{"objectType":"TwoColorsBall","subObjects":[{"type":"SpiderWeb","status":0}]},{"objectType":"ColorBall"},{"objectType":"ColorBall"},{"objectType":"ColorBall"},{"objectType":"ThunderBall"},{"objectType":"TwoColorsBall","subObjects":[{"type":"SpiderWeb","status":0}]},{"objectType":"TwoColorsBall","subObjects":[{"type":"SpiderWeb","status":0}]},{},{}],[{},{},{"objectType":"TwoColorsBall","subObjects":[{"type":"SpiderWeb","status":0}]},{"objectType":"TwoColorsBall","subObjects":[{"type":"SpiderWeb","status":0}]},{"objectType":"TwoColorsBall","subObjects":[{"type":"SpiderWeb","status":0}]},{"objectType":"ColorBall"},{"objectType":"ColorBall"},{"objectType":"ColorBall"},{"objectType":"TwoColorsBall","subObjects":[{"type":"SpiderWeb","status":0}]},{"objectType":"TwoColorsBall","subObjects":[{"type":"SpiderWeb","status":0}]},{"objectType":"TwoColorsBall","subObjects":[{"type":"SpiderWeb","status":0}]},{},{}],[{"objectType":"ColorBall"},{"objectType":"ColorBall"},{"objectType":"TwoColorsBall","subObjects":[{"type":"SpiderWeb","status":0}]},{"objectType":"ColorBomb"},{"objectType":"TwoColorsBall","subObjects":[{"type":"SpiderWeb","status":0}]},{},{},{"objectType":"TwoColorsBall","subObjects":[{"type":"SpiderWeb","status":0}]},{"objectType":"ColorBomb"},{"objectType":"TwoColorsBall","subObjects":[{"type":"SpiderWeb","status":0}]},{"objectType":"ColorBall"},{"objectType":"ColorBall"}],[{},{"objectType":"ColorBall"},{"objectType":"ColorBall"},{"objectType":"TwoColorsBall","subObjects":[{"type":"SpiderWeb","status":0}]},{"objectType":"TwoColorsBall","subObjects":[{"type":"SpiderWeb","status":0}]},{"objectType":"TwoColorsBall","subObjects":[{"type":"SpiderWeb","status":0}]},{},{"objectType":"TwoColorsBall","subObjects":[{"type":"SpiderWeb","status":0}]},{"objectType":"TwoColorsBall","subObjects":[{"type":"SpiderWeb","status":0}]},{"objectType":"TwoColorsBall","subObjects":[{"type":"SpiderWeb","status":0}]},{"objectType":"ColorBall"},{"objectType":"ColorBall"},{}],[{"objectType":"ColorBall"},{"objectType":"ColorBall"},{"objectType":"ColorBall"},{"objectType":"ColorBall"},{"objectType":"ThunderBall"},{},{},{"objectType":"ColorBall"},{"objectType":"ColorBall"},{"objectType":"ColorBall"},{"objectType":"ColorBall"},{"objectType":"ColorBall"}],[{"objectType":"ColorBall"},{"objectType":"ColorBall"},{"objectType":"ThunderBall","color":158691},{},{"objectType":"ColorBall"},{},{},{},{"objectType":"ColorBall"},{},{"objectType":"ColorBall"},{"objectType":"ColorBall","color":57396},{"objectType":"ColorBall"}],[{"objectType":"ColorBall"},{"objectType":"ColorBall"},{"objectType":"ColorBall","color":158691},{},{"objectType":"TwoColorsBall","subObjects":[{"type":"SpiderWeb","status":0}]},{"objectType":"ColorBall"},{"objectType":"ColorBall"},{"objectType":"TwoColorsBall","subObjects":[{"type":"SpiderWeb","status":0}]},{},{"objectType":"ColorBall"},{"objectType":"ThunderBall","color":57396},{"objectType":"ColorBall"}],[{},{},{"objectType":"ColorBall","color":158691},{},{"objectType":"ColorBall","color":16530738},{"objectType":"TwoColorsBall","subObjects":[{"type":"SpiderWeb","status":0}]},{"objectType":"ColorBomb"},{"objectType":"TwoColorsBall","subObjects":[{"type":"SpiderWeb","status":0}]},{"objectType":"ColorBall"},{},{"objectType":"ColorBall","color":57396},{},{}],[{},{},{},{},{"objectType":"TwoColorsBall","color":16530738,"subObjects":[{"type":"SpiderWeb","status":0}]},{"objectType":"ColorBall","color":16530738},{"objectType":"ColorBall","color":16763392},{"objectType":"TwoColorsBall","color":16763392,"subObjects":[{"type":"SpiderWeb","status":0}]},{},{},{},{}],[{},{},{},{},{},{},{"objectType":"ColorBall","color":16763392},{},{},{},{},{},{}]],"colorButtonOverlay":"orange"}